[
  {
    "id": 252,
    "name": "Treecko",
    "api_name": "treecko",
    "native_region": "Hoenn",
    "generation": 3,
    "type_1": "Grass",
    "type_2": "",
    "hp": 40,
    "attack": 45,
    "defense": 35,
    "special_attack": 65,
    "special_defense": 55,
    "speed": 70,
    "is_restricted": false
  },
  {
    "id": 253,
    "name": "Grovyle",
    "api_name": "grovyle",
    "native_region": "Hoenn",
    "generation": 3,
    "type_1": "Grass",
    "type_2": "",
    "hp": 50,
    "attack": 65,
    "defense": 45,
    "special_attack": 85,
    "special_defense": 65,
    "speed": 95,
    "is_restricted": false
  },
  {
    "id": 254,
    "name": "Sceptile",
    "api_name": "sceptile",
    "native_region": "Hoenn",
    "generation": 3,
    "type_1": "Grass",
    "type_2": "",
    "hp": 70,
    "attack": 85,
    "defense": 65,
    "special_attack": 105,
    "special_defense": 85,
    "speed": 120,
    "is_restricted": false
  },
  {
    "id": 255,
    "name": "Torchic",
    "api_name": "torchic",
    "native_region": "Hoenn",
    "generation": 3,
    "type_1": "Fire",
    "type_2": "",
    "hp": 45,
    "attack": 60,
    "defense": 40,
    "special_attack": 70,
    "special_defense": 50,
    "speed": 45,
    "is_restricted": false
  },
  {
    "id": 256,
    "name": "Combusken",
    "api_name": "combusken",
    "native_region": "Hoenn",
    "generation": 3,
    "type_1": "Fire",
    "type_2": "Fighting",
    "hp": 60,
    "attack": 85,
    "defense": 60,
    "special_attack": 85,
    "special_defense": 60,
    "speed": 55,
    "is_restricted": false
  },
  {
    "id": 257,
    "name": "Blaziken",
    "api_name": "blaziken",
    "native_region": "Hoenn",
    "generation": 3,
    "type_1": "Fire",
    "type_2": "Fighting",
    "hp": 80,
    "attack": 120,
    "defense": 70,
    "special_attack": 110,
    "special_defense": 70,
    "speed": 80,
    "is_restricted": false
  },
  {
    "id": 258,
    "name": "Mudkip",
    "api_name": "mudkip",
    "native_region": "Hoenn",
    "generation": 3,
    "type_1": "Water",
    "type_2": "",
    "hp": 50,
    "attack": 70,
    "defense": 50,
    "special_attack": 50,
    "special_defense": 50,
    "speed": 40,
    "is_restricted": false
  },
  {
    "id": 259,
    "name": "Marshtomp",
    "api_name": "marshtomp",
    "native_region": "Hoenn",
    "generation": 3,
    "type_1": "Water",
    "type_2": "Ground",
    "hp": 70,
    "attack": 85,
    "defense": 70,
    "special_attack": 60,
    "special_defense": 70,
    "speed": 50,
    "is_restricted": false
  },
  {
    "id": 260,
    "name": "Swampert",
    "api_name": "swampert",
    "native_region": "Hoenn",
    "generation": 3,
    "type_1": "Water",
    "type_2": "Ground",
    "hp": 100,
    "attack": 110,
    "defense": 90,
    "special_attack": 85,
    "special_defense": 90,
    "speed": 60,
    "is_restricted": false
  },
  {
    "id": 261,
    "name": "Poochyena",
    "api_name": "poochyena",
    "native_region": "Hoenn",
    "generation": 3,
    "type_1": "Dark",
    "type_2": "",
    "hp": 35,
    "attack": 55,
    "defense": 35,
    "special_attack": 30,
    "special_defense": 30,
    "speed": 35,
    "is_restricted": false
  },
  {
    "id": 262,
    "name": "Mightyena",
    "api_name": "mightyena",
    "native_region": "Hoenn",
    "generation": 3,
    "type_1": "Dark",
    "type_2": "",
    "hp": 70,
    "attack": 90,
    "defense": 70,
    "special_attack": 60,
    "special_defense": 60,
    "speed": 70,
    "is_restricted": false
  },
  {
    "id": 263,
    "name": "Zigzagoon",
    "api_name": "zigzagoon",
    "native_region": "Hoenn",
    "generation": 3,
    "type_1": "Normal",
    "type_2": "",
    "hp": 38,
    "attack": 30,
    "defense": 41,
    "special_attack": 30,
    "special_defense": 41,
    "speed": 60,
    "is_restricted": false
  },
  {
    "id": 264,
    "name": "Linoone",
    "api_name": "linoone",
    "native_region": "Hoenn",
    "generation": 3,
    "type_1": "Normal",
    "type_2": "",
    "hp": 78,
    "attack": 70,
    "defense": 61,
    "special_attack": 50,
    "special_defense": 61,
    "speed": 100,
    "is_restricted": false
  },
  {
    "id": 265,
    "name": "Wurmple",
    "api_name": "wurmple",
    "native_region": "Hoenn",
    "generation": 3,
    "type_1": "Bug",
    "type_2": "",
    "hp": 45,
    "attack": 45,
    "defense": 35,
    "special_attack": 20,
    "special_defense": 30,
    "speed": 20,
    "is_restricted": false
  },
  {
    "id": 266,
    "name": "Silcoon",
    "api_name": "silcoon",
    "native_region": "Hoenn",
    "generation": 3,
    "type_1": "Bug",
    "type_2": "",
    "hp": 50,
    "attack": 35,
    "defense": 55,
    "special_attack": 25,
    "special_defense": 25,
    "speed": 15,
    "is_restricted": false
  },
  {
    "id": 267,
    "name": "Beautifly",
    "api_name": "beautifly",
    "native_region": "Hoenn",
    "generation": 3,
    "type_1": "Bug",
    "type_2": "Flying",
    "hp": 60,
    "attack": 70,
    "defense": 50,
    "special_attack": 100,
    "special_defense": 50,
    "speed": 65,
    "is_restricted": false
  },
  {
    "id": 268,
    "name": "Cascoon",
    "api_name": "cascoon",
    "native_region": "Hoenn",
    "generation": 3,
    "type_1": "Bug",
    "type_2": "",
    "hp": 50,
    "attack": 35,
    "defense": 55,
    "special_attack": 25,
    "special_defense": 25,
    "speed": 15,
    "is_restricted": false
  },
  {
    "id": 269,
    "name": "Dustox",
    "api_name": "dustox",
    "native_region": "Hoenn",
    "generation": 3,
    "type_1": "Bug",
    "type_2": "Poison",
    "hp": 60,
    "attack": 50,
    "defense": 70,
    "special_attack": 50,
    "special_defense": 90,
    "speed": 65,
    "is_restricted": false
  },
  {
    "id": 270,
    "name": "Lotad",
    "api_name": "lotad",
    "native_region": "Hoenn",
    "generation": 3,
    "type_1": "Water",
    "type_2": "Grass",
    "hp": 40,
    "attack": 30,
    "defense": 30,
    "special_attack": 40,
    "special_defense": 50,
    "speed": 30,
    "is_restricted": false
  },
  {
    "id": 271,
    "name": "Lombre",
    "api_name": "lombre",
    "native_region": "Hoenn",
    "generation": 3,
    "type_1": "Water",
    "type_2": "Grass",
    "hp": 60,
    "attack": 50,
    "defense": 50,
    "special_attack": 60,
    "special_defense": 70,
    "speed": 50,
    "is_restricted": false
  },
  {
    "id": 272,
    "name": "Ludicolo",
    "api_name": "ludicolo",
    "native_region": "Hoenn",
    "generation": 3,
    "type_1": "Water",
    "type_2": "Grass",
    "hp": 80,
    "attack": 70,
    "defense": 70,
    "special_attack": 90,
    "special_defense": 100,
    "speed": 70,
    "is_restricted": false
  },
  {
    "id": 273,
    "name": "Seedot",
    "api_name": "seedot",
    "native_region": "Hoenn",
    "generation": 3,
    "type_1": "Grass",
    "type_2": "",
    "hp": 40,
    "attack": 40,
    "defense": 50,
    "special_attack": 30,
    "special_defense": 30,
    "speed": 30,
    "is_restricted": false
  },
  {
    "id": 274,
    "name": "Nuzleaf",
    "api_name": "nuzleaf",
    "native_region": "Hoenn",
    "generation": 3,
    "type_1": "Grass",
    "type_2": "Dark",
    "hp": 70,
    "attack": 70,
    "defense": 40,
    "special_attack": 60,
    "special_defense": 40,
    "speed": 60,
    "is_restricted": false
  },
  {
    "id": 275,
    "name": "Shiftry",
    "api_name": "shiftry",
    "native_region": "Hoenn",
    "generation": 3,
    "type_1": "Grass",
    "type_2": "Dark",
    "hp": 90,
    "attack": 100,
    "defense": 60,
    "special_attack": 90,
    "special_defense": 60,
    "speed": 80,
    "is_restricted": false
  },
  {
    "id": 276,
    "name": "Taillow",
    "api_name": "taillow",
    "native_region": "Hoenn",
    "generation": 3,
    "type_1": "Normal",
    "type_2": "Flying",
    "hp": 40,
    "attack": 55,
    "defense": 30,
    "special_attack": 30,
    "special_defense": 30,
    "speed": 85,
    "is_restricted": false
  },
  {
    "id": 277,
    "name": "Swellow",
    "api_name": "swellow",
    "native_region": "Hoenn",
    "generation": 3,
    "type_1": "Normal",
    "type_2": "Flying",
    "hp": 60,
    "attack": 85,
    "defense": 60,
    "special_attack": 75,
    "special_defense": 50,
    "speed": 125,
    "is_restricted": false
  },
  {
    "id": 278,
    "name": "Wingull",
    "api_name": "wingull",
    "native_region": "Hoenn",
    "generation": 3,
    "type_1": "Water",
    "type_2": "Flying",
    "hp": 40,
    "attack": 30,
    "defense": 30,
    "special_attack": 55,
    "special_defense": 30,
    "speed": 85,
    "is_restricted": false
  },
  {
    "id": 279,
    "name": "Pelipper",
    "api_name": "pelipper",
    "native_region": "Hoenn",
    "generation": 3,
    "type_1": "Water",
    "type_2": "Flying",
    "hp": 60,
    "attack": 50,
    "defense": 100,
    "special_attack": 95,
    "special_defense": 70,
    "speed": 65,
    "is_restricted": false
  },
  {
    "id": 280,
    "name": "Ralts",
    "api_name": "ralts",
    "native_region": "Hoenn",
    "generation": 3,
    "type_1": "Psychic",
    "type_2": "Fairy",
    "hp": 28,
    "attack": 25,
    "defense": 25,
    "special_attack": 45,
    "special_defense": 35,
    "speed": 40,
    "is_restricted": false
  },
  {
    "id": 281,
    "name": "Kirlia",
    "api_name": "kirlia",
    "native_region": "Hoenn",
    "generation": 3,
    "type_1": "Psychic",
    "type_2": "Fairy",
    "hp": 38,
    "attack": 35,
    "defense": 35,
    "special_attack": 65,
    "special_defense": 55,
    "speed": 50,
    "is_restricted": false
  },
  {
    "id": 282,
    "name": "Gardevoir",
    "api_name": "gardevoir",
    "native_region": "Hoenn",
    "generation": 3,
    "type_1": "Psychic",
    "type_2": "Fairy",
    "hp": 68,
    "attack": 65,
    "defense": 65,
    "special_attack": 125,
    "special_defense": 115,
    "speed": 80,
    "is_restricted": false
  },
  {
    "id": 283,
    "name": "Surskit",
    "api_name": "surskit",
    "native_region": "Hoenn",
    "generation": 3,
    "type_1": "Bug",
    "type_2": "Water",
    "hp": 40,
    "attack": 30,
    "defense": 32,
    "special_attack": 50,
    "special_defense": 52,
    "speed": 65,
    "is_restricted": false
  },
  {
    "id": 284,
    "name": "Masquerain",
    "api_name": "masquerain",
    "native_region": "Hoenn",
    "generation": 3,
    "type_1": "Bug",
    "type_2": "Flying",
    "hp": 70,
    "attack": 60,
    "defense": 62,
    "special_attack": 80,
    "special_defense": 82,
    "speed": 60,
    "is_restricted": false
  },
  {
    "id": 285,
    "name": "Shroomish",
    "api_name": "shroomish",
    "native_region": "Hoenn",
    "generation": 3,
    "type_1": "Grass",
    "type_2": "",
    "hp": 60,
    "attack": 40,
    "defense": 60,
    "special_attack": 40,
    "special_defense": 60,
    "speed": 35,
    "is_restricted": false
  },
  {
    "id": 286,
    "name": "Breloom",
    "api_name": "breloom",
    "native_region": "Hoenn",
    "generation": 3,
    "type_1": "Grass",
    "type_2": "Fighting",
    "hp": 60,
    "attack": 130,
    "defense": 80,
    "special_attack": 60,
    "special_defense": 60,
    "speed": 70,
    "is_restricted": false
  },
  {
    "id": 287,
    "name": "Slakoth",
    "api_name": "slakoth",
    "native_region": "Hoenn",
    "generation": 3,
    "type_1": "Normal",
    "type_2": "",
    "hp": 60,
    "attack": 60,
    "defense": 60,
    "special_attack": 35,
    "special_defense": 35,
    "speed": 30,
    "is_restricted": false
  },
  {
    "id": 288,
    "name": "Vigoroth",
    "api_name": "vigoroth",
    "native_region": "Hoenn",
    "generation": 3,
    "type_1": "Normal",
    "type_2": "",
    "hp": 80,
    "attack": 80,
    "defense": 80,
    "special_attack": 55,
    "special_defense": 55,
    "speed": 90,
    "is_restricted": false
  },
  {
    "id": 289,
    "name": "Slaking",
    "api_name": "slaking",
    "native_region": "Hoenn",
    "generation": 3,
    "type_1": "Normal",
    "type_2": "",
    "hp": 150,
    "attack": 160,
    "defense": 100,
    "special_attack": 95,
    "special_defense": 65,
    "speed": 100,
    "is_restricted": false
  },
  {
    "id": 290,
    "name": "Nincada",
    "api_name": "nincada",
    "native_region": "Hoenn",
    "generation": 3,
    "type_1": "Bug",
    "type_2": "Ground",
    "hp": 31,
    "attack": 45,
    "defense": 90,
    "special_attack": 30,
    "special_defense": 30,
    "speed": 40,
    "is_restricted": false
  },
  {
    "id": 291,
    "name": "Ninjask",
    "api_name": "ninjask",
    "native_region": "Hoenn",
    "generation": 3,
    "type_1": "Bug",
    "type_2": "Flying",
    "hp": 61,
    "attack": 90,
    "defense": 45,
    "special_attack": 50,
    "special_defense": 50,
    "speed": 160,
    "is_restricted": false
  },
  {
    "id": 292,
    "name": "Shedinja",
    "api_name": "shedinja",
    "native_region": "Hoenn",
    "generation": 3,
    "type_1": "Bug",
    "type_2": "Ghost",
    "hp": 1,
    "attack": 90,
    "defense": 45,
    "special_attack": 30,
    "special_defense": 30,
    "speed": 40,
    "is_restricted": false
  },
  {
    "id": 293,
    "name": "Whismur",
    "api_name": "whismur",
    "native_region": "Hoenn",
    "generation": 3,
    "type_1": "Normal",
    "type_2": "",
    "hp": 64,
    "attack": 51,
    "defense": 23,
    "special_attack": 51,
    "special_defense": 23,
    "speed": 28,
    "is_restricted": false
  },
  {
    "id": 294,
    "name": "Loudred",
    "api_name": "loudred",
    "native_region": "Hoenn",
    "generation": 3,
    "type_1": "Normal",
    "type_2": "",
    "hp": 84,
    "attack": 71,
    "defense": 43,
    "special_attack": 71,
    "special_defense": 43,
    "speed": 48,
    "is_restricted": false
  },
  {
    "id": 295,
    "name": "Exploud",
    "api_name": "exploud",
    "native_region": "Hoenn",
    "generation": 3,
    "type_1": "Normal",
    "type_2": "",
    "hp": 104,
    "attack": 91,
    "defense": 63,
    "special_attack": 91,
    "special_defense": 73,
    "speed": 68,
    "is_restricted": false
  },
  {
    "id": 296,
    "name": "Makuhita",
    "api_name": "makuhita",
    "native_region": "Hoenn",
    "generation": 3,
    "type_1": "Fighting",
    "type_2": "",
    "hp": 72,
    "attack": 60,
    "defense": 30,
    "special_attack": 20,
    "special_defense": 30,
    "speed": 25,
    "is_restricted": false
  },
  {
    "id": 297,
    "name": "Hariyama",
    "api_name": "hariyama",
    "native_region": "Hoenn",
    "generation": 3,
    "type_1": "Fighting",
    "type_2": "",
    "hp": 144,
    "attack": 120,
    "defense": 60,
    "special_attack": 40,
    "special_defense": 60,
    "speed": 50,
    "is_restricted": false
  },
  {
    "id": 299,
    "name": "Nosepass",
    "api_name": "nosepass",
    "native_region": "Hoenn",
    "generation": 3,
    "type_1": "Rock",
    "type_2": "",
    "hp": 30,
    "attack": 45,
    "defense": 135,
    "special_attack": 45,
    "special_defense": 90,
    "speed": 30,
    "is_restricted": false
  },
  {
    "id": 300,
    "name": "Skitty",
    "api_name": "skitty",
    "native_region": "Hoenn",
    "generation": 3,
    "type_1": "Normal",
    "type_2": "",
    "hp": 50,
    "attack": 45,
    "defense": 45,
    "special_attack": 35,
    "special_defense": 35,
    "speed": 50,
    "is_restricted": false
  },
  {
    "id": 301,
    "name": "Delcatty",
    "api_name": "delcatty",
    "native_region": "Hoenn",
    "generation": 3,
    "type_1": "Normal",
    "type_2": "",
    "hp": 70,
    "attack": 65,
    "defense": 65,
    "special_attack": 55,
    "special_defense": 55,
    "speed": 70,
    "is_restricted": false
  },
  {
    "id": 302,
    "name": "Sableye",
    "api_name": "sableye",
    "native_region": "Hoenn",
    "generation": 3,
    "type_1": "Dark",
    "type_2": "Ghost",
    "hp": 50,
    "attack": 75,
    "defense": 75,
    "special_attack": 65,
    "special_defense": 65,
    "speed": 50,
    "is_restricted": false
  },
  {
    "id": 303,
    "name": "Mawile",
    "api_name": "mawile",
    "native_region": "Hoenn",
    "generation": 3,
    "type_1": "Steel",
    "type_2": "Fairy",
    "hp": 50,
    "attack": 85,
    "defense": 85,
    "special_attack": 55,
    "special_defense": 55,
    "speed": 50,
    "is_restricted": false
  },
  {
    "id": 304,
    "name": "Aron",
    "api_name": "aron",
    "native_region": "Hoenn",
    "generation": 3,
    "type_1": "Steel",
    "type_2": "Rock",
    "hp": 50,
    "attack": 70,
    "defense": 100,
    "special_attack": 40,
    "special_defense": 40,
    "speed": 30,
    "is_restricted": false
  },
  {
    "id": 305,
    "name": "Lairon",
    "api_name": "lairon",
    "native_region": "Hoenn",
    "generation": 3,
    "type_1": "Steel",
    "type_2": "Rock",
    "hp": 60,
    "attack": 90,
    "defense": 140,
    "special_attack": 50,
    "special_defense": 50,
    "speed": 40,
    "is_restricted": false
  },
  {
    "id": 306,
    "name": "Aggron",
    "api_name": "aggron",
    "native_region": "Hoenn",
    "generation": 3,
    "type_1": "Steel",
    "type_2": "Rock",
    "hp": 70,
    "attack": 110,
    "defense": 180,
    "special_attack": 60,
    "special_defense": 60,
    "speed": 50,
    "is_restricted": false
  },
  {
    "id": 307,
    "name": "Meditite",
    "api_name": "meditite",
    "native_region": "Hoenn",
    "generation": 3,
    "type_1": "Fighting",
    "type_2": "Psychic",
    "hp": 30,
    "attack": 40,
    "defense": 55,
    "special_attack": 40,
    "special_defense": 55,
    "speed": 60,
    "is_restricted": false
  },
  {
    "id": 308,
    "name": "Medicham",
    "api_name": "medicham",
    "native_region": "Hoenn",
    "generation": 3,
    "type_1": "Fighting",
    "type_2": "Psychic",
    "hp": 60,
    "attack": 60,
    "defense": 75,
    "special_attack": 60,
    "special_defense": 75,
    "speed": 80,
    "is_restricted": false
  },
  {
    "id": 309,
    "name": "Electrike",
    "api_name": "electrike",
    "native_region": "Hoenn",
    "generation": 3,
    "type_1": "Electric",
    "type_2": "",
    "hp": 40,
    "attack": 45,
    "defense": 40,
    "special_attack": 65,
    "special_defense": 40,
    "speed": 65,
    "is_restricted": false
  },
  {
    "id": 310,
    "name": "Manectric",
    "api_name": "manectric",
    "native_region": "Hoenn",
    "generation": 3,
    "type_1": "Electric",
    "type_2": "",
    "hp": 70,
    "attack": 75,
    "defense": 60,
    "special_attack": 105,
    "special_defense": 60,
    "speed": 105,
    "is_restricted": false
  },
  {
    "id": 311,
    "name": "Plusle",
    "api_name": "plusle",
    "native_region": "Hoenn",
    "generation": 3,
    "type_1": "Electric",
    "type_2": "",
    "hp": 60,
    "attack": 50,
    "defense": 40,
    "special_attack": 85,
    "special_defense": 75,
    "speed": 95,
    "is_restricted": false
  },
  {
    "id": 312,
    "name": "Minun",
    "api_name": "minun",
    "native_region": "Hoenn",
    "generation": 3,
    "type_1": "Electric",
    "type_2": "",
    "hp": 60,
    "attack": 40,
    "defense": 50,
    "special_attack": 75,
    "special_defense": 85,
    "speed": 95,
    "is_restricted": false
  },
  {
    "id": 313,
    "name": "Volbeat",
    "api_name": "volbeat",
    "native_region": "Hoenn",
    "generation": 3,
    "type_1": "Bug",
    "type_2": "",
    "hp": 65,
    "attack": 73,
    "defense": 75,
    "special_attack": 47,
    "special_defense": 85,
    "speed": 85,
    "is_restricted": false
  },
  {
    "id": 314,
    "name": "Illumise",
    "api_name": "illumise",
    "native_region": "Hoenn",
    "generation": 3,
    "type_1": "Bug",
    "type_2": "",
    "hp": 65,
    "attack": 47,
    "defense": 75,
    "special_attack": 73,
    "special_defense": 85,
    "speed": 85,
    "is_restricted": false
  },
  {
    "id": 315,
    "name": "Roselia",
    "api_name": "roselia",
    "native_region": "Hoenn",
    "generation": 3,
    "type_1": "Grass",
    "type_2": "Poison",
    "hp": 50,
    "attack": 60,
    "defense": 45,
    "special_attack": 100,
    "special_defense": 80,
    "speed": 65,
    "is_restricted": false
  },
  {
    "id": 316,
    "name": "Gulpin",
    "api_name": "gulpin",
    "native_region": "Hoenn",
    "generation": 3,
    "type_1": "Poison",
    "type_2": "",
    "hp": 70,
    "attack": 43,
    "defense": 53,
    "special_attack": 43,
    "special_defense": 53,
    "speed": 40,
    "is_restricted": false
  },
  {
    "id": 317,
    "name": "Swalot",
    "api_name": "swalot",
    "native_region": "Hoenn",
    "generation": 3,
    "type_1": "Poison",
    "type_2": "",
    "hp": 100,
    "attack": 73,
    "defense": 83,
    "special_attack": 73,
    "special_defense": 83,
    "speed": 55,
    "is_restricted": false
  },
  {
    "id": 318,
    "name": "Carvanha",
    "api_name": "carvanha",
    "native_region": "Hoenn",
    "generation": 3,
    "type_1": "Water",
    "type_2": "Dark",
    "hp": 45,
    "attack": 90,
    "defense": 20,
    "special_attack": 65,
    "special_defense": 20,
    "speed": 65,
    "is_restricted": false
  },
  {
    "id": 319,
    "name": "Sharpedo",
    "api_name": "sharpedo",
    "native_region": "Hoenn",
    "generation": 3,
    "type_1": "Water",
    "type_2": "Dark",
    "hp": 70,
    "attack": 120,
    "defense": 40,
    "special_attack": 95,
    "special_defense": 40,
    "speed": 95,
    "is_restricted": false
  },
  {
    "id": 320,
    "name": "Wailmer",
    "api_name": "wailmer",
    "native_region": "Hoenn",
    "generation": 3,
    "type_1": "Water",
    "type_2": "",
    "hp": 130,
    "attack": 70,
    "defense": 35,
    "special_attack": 70,
    "special_defense": 35,
    "speed": 60,
    "is_restricted": false
  },
  {
    "id": 321,
    "name": "Wailord",
    "api_name": "wailord",
    "native_region": "Hoenn",
    "generation": 3,
    "type_1": "Water",
    "type_2": "",
    "hp": 170,
    "attack": 90,
    "defense": 45,
    "special_attack": 90,
    "special_defense": 45,
    "speed": 60,
    "is_restricted": false
  },
  {
    "id": 322,
    "name": "Numel",
    "api_name": "numel",
    "native_region": "Hoenn",
    "generation": 3,
    "type_1": "Fire",
    "type_2": "Ground",
    "hp": 60,
    "attack": 60,
    "defense": 40,
    "special_attack": 65,
    "special_defense": 45,
    "speed": 35,
    "is_restricted": false
  },
  {
    "id": 323,
    "name": "Camerupt",
    "api_name": "camerupt",
    "native_region": "Hoenn",
    "generation": 3,
    "type_1": "Fire",
    "type_2": "Ground",
    "hp": 70,
    "attack": 100,
    "defense": 70,
    "special_attack": 105,
    "special_defense": 75,
    "speed": 40,
    "is_restricted": false
  },
  {
    "id": 324,
    "name": "Torkoal",
    "api_name": "torkoal",
    "native_region": "Hoenn",
    "generation": 3,
    "type_1": "Fire",
    "type_2": "",
    "hp": 70,
    "attack": 85,
    "defense": 140,
    "special_attack": 85,
    "special_defense": 70,
    "speed": 20,
    "is_restricted": false
  },
  {
    "id": 325,
    "name": "Spoink",
    "api_name": "spoink",
    "native_region": "Hoenn",
    "generation": 3,
    "type_1": "Psychic",
    "type_2": "",
    "hp": 60,
    "attack": 25,
    "defense": 35,
    "special_attack": 70,
    "special_defense": 80,
    "speed": 60,
    "is_restricted": false
  },
  {
    "id": 326,
    "name": "Grumpig",
    "api_name": "grumpig",
    "native_region": "Hoenn",
    "generation": 3,
    "type_1": "Psychic",
    "type_2": "",
    "hp": 80,
    "attack": 45,
    "defense": 65,
    "special_attack": 90,
    "special_defense": 110,
    "speed": 80,
    "is_restricted": false
  },
  {
    "id": 327,
    "name": "Spinda",
    "api_name": "spinda",
    "native_region": "Hoenn",
    "generation": 3,
    "type_1": "Normal",
    "type_2": "",
    "hp": 60,
    "attack": 60,
    "defense": 60,
    "special_attack": 60,
    "special_defense": 60,
    "speed": 60,
    "is_restricted": false
  },
  {
    "id": 328,
    "name": "Trapinch",
    "api_name": "trapinch",
    "native_region": "Hoenn",
    "generation": 3,
    "type_1": "Ground",
    "type_2": "",
    "hp": 45,
    "attack": 100,
    "defense": 45,
    "special_attack": 45,
    "special_defense": 45,
    "speed": 10,
    "is_restricted": false
  },
  {
    "id": 329,
    "name": "Vibrava",
    "api_name": "vibrava",
    "native_region": "Hoenn",
    "generation": 3,
    "type_1": "Ground",
    "type_2": "Dragon",
    "hp": 50,
    "attack": 70,
    "defense": 50,
    "special_attack": 50,
    "special_defense": 50,
    "speed": 70,
    "is_restricted": false
  },
  {
    "id": 330,
    "name": "Flygon",
    "api_name": "flygon",
    "native_region": "Hoenn",
    "generation": 3,
    "type_1": "Ground",
    "type_2": "Dragon",
    "hp": 80,
    "attack": 100,
    "defense": 80,
    "special_attack": 80,
    "special_defense": 80,
    "speed": 100,
    "is_restricted": false
  },
  {
    "id": 331,
    "name": "Cacnea",
    "api_name": "cacnea",
    "native_region": "Hoenn",
    "generation": 3,
    "type_1": "Grass",
    "type_2": "",
    "hp": 50,
    "attack": 85,
    "defense": 40,
    "special_attack": 85,
    "special_defense": 40,
    "speed": 35,
    "is_restricted": false
  },
  {
    "id": 332,
    "name": "Cacturne",
    "api_name": "cacturne",
    "native_region": "Hoenn",
    "generation": 3,
    "type_1": "Grass",
    "type_2": "Dark",
    "hp": 70,
    "attack": 115,
    "defense": 60,
    "special_attack": 115,
    "special_defense": 60,
    "speed": 55,
    "is_restricted": false
  },
  {
    "id": 333,
    "name": "Swablu",
    "api_name": "swablu",
    "native_region": "Hoenn",
    "generation": 3,
    "type_1": "Normal",
    "type_2": "Flying",
    "hp": 45,
    "attack": 40,
    "defense": 60,
    "special_attack": 40,
    "special_defense": 75,
    "speed": 50,
    "is_restricted": false
  },
  {
    "id": 334,
    "name": "Altaria",
    "api_name": "altaria",
    "native_region": "Hoenn",
    "generation": 3,
    "type_1": "Dragon",
    "type_2": "Flying",
    "hp": 75,
    "attack": 70,
    "defense": 90,
    "special_attack": 70,
    "special_defense": 105,
    "speed": 80,
    "is_restricted": false
  },
  {
    "id": 335,
    "name": "Zangoose",
    "api_name": "zangoose",
    "native_region": "Hoenn",
    "generation": 3,
    "type_1": "Normal",
    "type_2": "",
    "hp": 73,
    "attack": 115,
    "defense": 60,
    "special_attack": 60,
    "special_defense": 60,
    "speed": 90,
    "is_restricted": false
  },
  {
    "id": 336,
    "name": "Seviper",
    "api_name": "seviper",
    "native_region": "Hoenn",
    "generation": 3,
    "type_1": "Poison",
    "type_2": "",
    "hp": 73,
    "attack": 100,
    "defense": 60,
    "special_attack": 100,
    "special_defense": 60,
    "speed": 65,
    "is_restricted": false
  },
  {
    "id": 337,
    "name": "Lunatone",
    "api_name": "lunatone",
    "native_region": "Hoenn",
    "generation": 3,
    "type_1": "Rock",
    "type_2": "Psychic",
    "hp": 90,
    "attack": 55,
    "defense": 65,
    "special_attack": 95,
    "special_defense": 85,
    "speed": 70,
    "is_restricted": false
  },
  {
    "id": 338,
    "name": "Solrock",
    "api_name": "solrock",
    "native_region": "Hoenn",
    "generation": 3,
    "type_1": "Rock",
    "type_2": "Psychic",
    "hp": 90,
    "attack": 95,
    "defense": 85,
    "special_attack": 55,
    "special_defense": 65,
    "speed": 70,
    "is_restricted": false
  },
  {
    "id": 339,
    "name": "Barboach",
    "api_name": "barboach",
    "native_region": "Hoenn",
    "generation": 3,
    "type_1": "Water",
    "type_2": "Ground",
    "hp": 50,
    "attack": 48,
    "defense": 43,
    "special_attack": 46,
    "special_defense": 41,
    "speed": 60,
    "is_restricted": false
  },
  {
    "id": 340,
    "name": "Whiscash",
    "api_name": "whiscash",
    "native_region": "Hoenn",
    "generation": 3,
    "type_1": "Water",
    "type_2": "Ground",
    "hp": 110,
    "attack": 78,
    "defense": 73,
    "special_attack": 76,
    "special_defense": 71,
    "speed": 60,
    "is_restricted": false
  },
  {
    "id": 341,
    "name": "Corphish",
    "api_name": "corphish",
    "native_region": "Hoenn",
    "generation": 3,
    "type_1": "Water",
    "type_2": "",
    "hp": 43,
    "attack": 80,
    "defense": 65,
    "special_attack": 50,
    "special_defense": 35,
    "speed": 35,
    "is_restricted": false
  },
  {
    "id": 342,
    "name": "Crawdaunt",
    "api_name": "crawdaunt",
    "native_region": "Hoenn",
    "generation": 3,
    "type_1": "Water",
    "type_2": "Dark",
    "hp": 63,
    "attack": 120,
    "defense": 85,
    "special_attack": 90,
    "special_defense": 55,
    "speed": 55,
    "is_restricted": false
  },
  {
    "id": 343,
    "name": "Baltoy",
    "api_name": "baltoy",
    "native_region": "Hoenn",
    "generation": 3,
    "type_1": "Ground",
    "type_2": "Psychic",
    "hp": 40,
    "attack": 40,
    "defense": 55,
    "special_attack": 40,
    "special_defense": 70,
    "speed": 55,
    "is_restricted": false
  },
  {
    "id": 344,
    "name": "Claydol",
    "api_name": "claydol",
    "native_region": "Hoenn",
    "generation": 3,
    "type_1": "Ground",
    "type_2": "Psychic",
    "hp": 60,
    "attack": 70,
    "defense": 105,
    "special_attack": 70,
    "special_defense": 120,
    "speed": 75,
    "is_restricted": false
  },
  {
    "id": 345,
    "name": "Lileep",
    "api_name": "lileep",
    "native_region": "Hoenn",
    "generation": 3,
    "type_1": "Rock",
    "type_2": "Grass",
    "hp": 66,
    "attack": 41,
    "defense": 77,
    "special_attack": 61,
    "special_defense": 87,
    "speed": 23,
    "is_restricted": false
  },
  {
    "id": 346,
    "name": "Cradily",
    "api_name": "cradily",
    "native_region": "Hoenn",
    "generation": 3,
    "type_1": "Rock",
    "type_2": "Grass",
    "hp": 86,
    "attack": 81,
    "defense": 97,
    "special_attack": 81,
    "special_defense": 107,
    "speed": 43,
    "is_restricted": false
  },
  {
    "id": 347,
    "name": "Anorith",
    "api_name": "anorith",
    "native_region": "Hoenn",
    "generation": 3,
    "type_1": "Rock",
    "type_2": "Bug",
    "hp": 45,
    "attack": 95,
    "defense": 50,
    "special_attack": 40,
    "special_defense": 50,
    "speed": 75,
    "is_restricted": false
  },
  {
    "id": 348,
    "name": "Armaldo",
    "api_name": "armaldo",
    "native_region": "Hoenn",
    "generation": 3,
    "type_1": "Rock",
    "type_2": "Bug",
    "hp": 75,
    "attack": 125,
    "defense": 100,
    "special_attack": 70,
    "special_defense": 80,
    "speed": 45,
    "is_restricted": false
  },
  {
    "id": 349,
    "name": "Feebas",
    "api_name": "feebas",
    "native_region": "Hoenn",
    "generation": 3,
    "type_1": "Water",
    "type_2": "",
    "hp": 20,
    "attack": 15,
    "defense": 20,
    "special_attack": 10,
    "special_defense": 55,
    "speed": 80,
    "is_restricted": false
  },
  {
    "id": 350,
    "name": "Milotic",
    "api_name": "milotic",
    "native_region": "Hoenn",
    "generation": 3,
    "type_1": "Water",
    "type_2": "",
    "hp": 95,
    "attack": 60,
    "defense": 79,
    "special_attack": 100,
    "special_defense": 125,
    "speed": 81,
    "is_restricted": false
  },
  {
    "id": 351,
    "name": "Castform",
    "api_name": "castform",
    "native_region": "Hoenn",
    "generation": 3,
    "type_1": "Normal",
    "type_2": "",
    "hp": 70,
    "attack": 70,
    "defense": 70,
    "special_attack": 70,
    "special_defense": 70,
    "speed": 70,
    "is_restricted": false
  },
  {
    "id": 352,
    "name": "Kecleon",
    "api_name": "kecleon",
    "native_region": "Hoenn",
    "generation": 3,
    "type_1": "Normal",
    "type_2": "",
    "hp": 60,
    "attack": 90,
    "defense": 70,
    "special_attack": 60,
    "special_defense": 120,
    "speed": 40,
    "is_restricted": false
  },
  {
    "id": 353,
    "name": "Shuppet",
    "api_name": "shuppet",
    "native_region": "Hoenn",
    "generation": 3,
    "type_1": "Ghost",
    "type_2": "",
    "hp": 44,
    "attack": 75,
    "defense": 35,
    "special_attack": 63,
    "special_defense": 33,
    "speed": 45,
    "is_restricted": false
  },
  {
    "id": 354,
    "name": "Banette",
    "api_name": "banette",
    "native_region": "Hoenn",
    "generation": 3,
    "type_1": "Ghost",
    "type_2": "",
    "hp": 64,
    "attack": 115,
    "defense": 65,
    "special_attack": 83,
    "special_defense": 63,
    "speed": 65,
    "is_restricted": false
  },
  {
    "id": 355,
    "name": "Duskull",
    "api_name": "duskull",
    "native_region": "Hoenn",
    "generation": 3,
    "type_1": "Ghost",
    "type_2": "",
    "hp": 20,
    "attack": 40,
    "defense": 90,
    "special_attack": 30,
    "special_defense": 90,
    "speed": 25,
    "is_restricted": false
  },
  {
    "id": 356,
    "name": "Dusclops",
    "api_name": "dusclops",
    "native_region": "Hoenn",
    "generation": 3,
    "type_1": "Ghost",
    "type_2": "",
    "hp": 40,
    "attack": 70,
    "defense": 130,
    "special_attack": 60,
    "special_defense": 130,
    "speed": 25,
    "is_restricted": false
  },
  {
    "id": 357,
    "name": "Tropius",
    "api_name": "tropius",
    "native_region": "Hoenn",
    "generation": 3,
    "type_1": "Grass",
    "type_2": "Flying",
    "hp": 99,
    "attack": 68,
    "defense": 83,
    "special_attack": 72,
    "special_defense": 87,
    "speed": 51,
    "is_restricted": false
  },
  {
    "id": 358,
    "name": "Chimecho",
    "api_name": "chimecho",
    "native_region": "Hoenn",
    "generation": 3,
    "type_1": "Psychic",
    "type_2": "",
    "hp": 65,
    "attack": 50,
    "defense": 70,
    "special_attack": 95,
    "special_defense": 80,
    "speed": 65,
    "is_restricted": false
  },
  {
    "id": 359,
    "name": "Absol",
    "api_name": "absol",
    "native_region": "Hoenn",
    "generation": 3,
    "type_1": "Dark",
    "type_2": "",
    "hp": 65,
    "attack": 130,
    "defense": 60,
    "special_attack": 75,
    "special_defense": 60,
    "speed": 75,
    "is_restricted": false
  },
  {
    "id": 361,
    "name": "Snorunt",
    "api_name": "snorunt",
    "native_region": "Hoenn",
    "generation": 3,
    "type_1": "Ice",
    "type_2": "",
    "hp": 50,
    "attack": 50,
    "defense": 50,
    "special_attack": 50,
    "special_defense": 50,
    "speed": 50,
    "is_restricted": false
  },
  {
    "id": 362,
    "name": "Glalie",
    "api_name": "glalie",
    "native_region": "Hoenn",
    "generation": 3,
    "type_1": "Ice",
    "type_2": "",
    "hp": 80,
    "attack": 80,
    "defense": 80,
    "special_attack": 80,
    "special_defense": 80,
    "speed": 80,
    "is_restricted": false
  },
  {
    "id": 363,
    "name": "Spheal",
    "api_name": "spheal",
    "native_region": "Hoenn",
    "generation": 3,
    "type_1": "Ice",
    "type_2": "Water",
    "hp": 70,
    "attack": 40,
    "defense": 50,
    "special_attack": 55,
    "special_defense": 50,
    "speed": 25,
    "is_restricted": false
  },
  {
    "id": 364,
    "name": "Sealeo",
    "api_name": "sealeo",
    "native_region": "Hoenn",
    "generation": 3,
    "type_1": "Ice",
    "type_2": "Water",
    "hp": 90,
    "attack": 60,
    "defense": 70,
    "special_attack": 75,
    "special_defense": 70,
    "speed": 45,
    "is_restricted": false
  },
  {
    "id": 365,
    "name": "Walrein",
    "api_name": "walrein",
    "native_region": "Hoenn",
    "generation": 3,
    "type_1": "Ice",
    "type_2": "Water",
    "hp": 110,
    "attack": 80,
    "defense": 90,
    "special_attack": 95,
    "special_defense": 90,
    "speed": 65,
    "is_restricted": false
  },
  {
    "id": 366,
    "name": "Clamperl",
    "api_name": "clamperl",
    "native_region": "Hoenn",
    "generation": 3,
    "type_1": "Water",
    "type_2": "",
    "hp": 35,
    "attack": 64,
    "defense": 85,
    "special_attack": 74,
    "special_defense": 55,
    "speed": 32,
    "is_restricted": false
  },
  {
    "id": 367,
    "name": "Huntail",
    "api_name": "huntail",
    "native_region": "Hoenn",
    "generation": 3,
    "type_1": "Water",
    "type_2": "",
    "hp": 55,
    "attack": 104,
    "defense": 105,
    "special_attack": 94,
    "special_defense": 75,
    "speed": 52,
    "is_restricted": false
  },
  {
    "id": 368,
    "name": "Gorebyss",
    "api_name": "gorebyss",
    "native_region": "Hoenn",
    "generation": 3,
    "type_1": "Water",
    "type_2": "",
    "hp": 55,
    "attack": 84,
    "defense": 105,
    "special_attack": 114,
    "special_defense": 75,
    "speed": 52,
    "is_restricted": false
  },
  {
    "id": 369,
    "name": "Relicanth",
    "api_name": "relicanth",
    "native_region": "Hoenn",
    "generation": 3,
    "type_1": "Water",
    "type_2": "Rock",
    "hp": 100,
    "attack": 90,
    "defense": 130,
    "special_attack": 45,
    "special_defense": 65,
    "speed": 55,
    "is_restricted": false
  },
  {
    "id": 370,
    "name": "Luvdisc",
    "api_name": "luvdisc",
    "native_region": "Hoenn",
    "generation": 3,
    "type_1": "Water",
    "type_2": "",
    "hp": 43,
    "attack": 30,
    "defense": 55,
    "special_attack": 40,
    "special_defense": 65,
    "speed": 97,
    "is_restricted": false
  },
  {
    "id": 371,
    "name": "Bagon",
    "api_name": "bagon",
    "native_region": "Hoenn",
    "generation": 3,
    "type_1": "Dragon",
    "type_2": "",
    "hp": 45,
    "attack": 75,
    "defense": 60,
    "special_attack": 40,
    "special_defense": 30,
    "speed": 50,
    "is_restricted": false
  },
  {
    "id": 372,
    "name": "Shelgon",
    "api_name": "shelgon",
    "native_region": "Hoenn",
    "generation": 3,
    "type_1": "Dragon",
    "type_2": "",
    "hp": 65,
    "attack": 95,
    "defense": 100,
    "special_attack": 60,
    "special_defense": 50,
    "speed": 50,
    "is_restricted": false
  },
  {
    "id": 373,
    "name": "Salamence",
    "api_name": "salamence",
    "native_region": "Hoenn",
    "generation": 3,
    "type_1": "Dragon",
    "type_2": "Flying",
    "hp": 95,
    "attack": 135,
    "defense": 80,
    "special_attack": 110,
    "special_defense": 80,
    "speed": 100,
    "is_restricted": false
  },
  {
    "id": 374,
    "name": "Beldum",
    "api_name": "beldum",
    "native_region": "Hoenn",
    "generation": 3,
    "type_1": "Steel",
    "type_2": "Psychic",
    "hp": 40,
    "attack": 55,
    "defense": 80,
    "special_attack": 35,
    "special_defense": 60,
    "speed": 30,
    "is_restricted": false
  },
  {
    "id": 375,
    "name": "Metang",
    "api_name": "metang",
    "native_region": "Hoenn",
    "generation": 3,
    "type_1": "Steel",
    "type_2": "Psychic",
    "hp": 60,
    "attack": 75,
    "defense": 100,
    "special_attack": 55,
    "special_defense": 80,
    "speed": 50,
    "is_restricted": false
  },
  {
    "id": 376,
    "name": "Metagross",
    "api_name": "metagross",
    "native_region": "Hoenn",
    "generation": 3,
    "type_1": "Steel",
    "type_2": "Psychic",
    "hp": 80,
    "attack": 135,
    "defense": 130,
    "special_attack": 95,
    "special_defense": 90,
    "speed": 70,
    "is_restricted": false
  },
  {
    "id": 387,
    "name": "Turtwig",
    "api_name": "turtwig",
    "native_region": "Sinnoh",
    "generation": 4,
    "type_1": "Grass",
    "type_2": "",
    "hp": 55,
    "attack": 68,
    "defense": 64,
    "special_attack": 45,
    "special_defense": 55,
    "speed": 31,
    "is_restricted": false
  },
  {
    "id": 388,
    "name": "Grotle",
    "api_name": "grotle",
    "native_region": "Sinnoh",
    "generation": 4,
    "type_1": "Grass",
    "type_2": "",
    "hp": 75,
    "attack": 89,
    "defense": 85,
    "special_attack": 55,
    "special_defense": 65,
    "speed": 36,
    "is_restricted": false
  },
  {
    "id": 389,
    "name": "Torterra",
    "api_name": "torterra",
    "native_region": "Sinnoh",
    "generation": 4,
    "type_1": "Grass",
    "type_2": "Ground",
    "hp": 95,
    "attack": 109,
    "defense": 105,
    "special_attack": 75,
    "special_defense": 85,
    "speed": 56,
    "is_restricted": false
  },
  {
    "id": 390,
    "name": "Chimchar",
    "api_name": "chimchar",
    "native_region": "Sinnoh",
    "generation": 4,
    "type_1": "Fire",
    "type_2": "",
    "hp": 44,
    "attack": 58,
    "defense": 44,
    "special_attack": 58,
    "special_defense": 44,
    "speed": 61,
    "is_restricted": false
  },
  {
    "id": 391,
    "name": "Monferno",
    "api_name": "monferno",
    "native_region": "Sinnoh",
    "generation": 4,
    "type_1": "Fire",
    "type_2": "Fighting",
    "hp": 64,
    "attack": 78,
    "defense": 52,
    "special_attack": 78,
    "special_defense": 52,
    "speed": 81,
    "is_restricted": false
  },
  {
    "id": 392,
    "name": "Infernape",
    "api_name": "infernape",
    "native_region": "Sinnoh",
    "generation": 4,
    "type_1": "Fire",
    "type_2": "Fighting",
    "hp": 76,
    "attack": 104,
    "defense": 71,
    "special_attack": 104,
    "special_defense": 71,
    "speed": 108,
    "is_restricted": false
  },
  {
    "id": 393,
    "name": "Piplup",
    "api_name": "piplup",
    "native_region": "Sinnoh",
    "generation": 4,
    "type_1": "Water",
    "type_2": "",
    "hp": 53,
    "attack": 51,
    "defense": 53,
    "special_attack": 61,
    "special_defense": 56,
    "speed": 40,
    "is_restricted": false
  },
  {
    "id": 394,
    "name": "Prinplup",
    "api_name": "prinplup",
    "native_region": "Sinnoh",
    "generation": 4,
    "type_1": "Water",
    "type_2": "",
    "hp": 64,
    "attack": 66,
    "defense": 68,
    "special_attack": 81,
    "special_defense": 76,
    "speed": 50,
    "is_restricted": false
  },
  {
    "id": 395,
    "name": "Empoleon",
    "api_name": "empoleon",
    "native_region": "Sinnoh",
    "generation": 4,
    "type_1": "Water",
    "type_2": "Steel",
    "hp": 84,
    "attack": 86,
    "defense": 88,
    "special_attack": 111,
    "special_defense": 101,
    "speed": 60,
    "is_restricted": false
  },
  {
    "id": 396,
    "name": "Starly",
    "api_name": "starly",
    "native_region": "Sinnoh",
    "generation": 4,
    "type_1": "Normal",
    "type_2": "Flying",
    "hp": 40,
    "attack": 55,
    "defense": 30,
    "special_attack": 30,
    "special_defense": 30,
    "speed": 60,
    "is_restricted": false
  },
  {
    "id": 397,
    "name": "Staravia",
    "api_name": "staravia",
    "native_region": "Sinnoh",
    "generation": 4,
    "type_1": "Normal",
    "type_2": "Flying",
    "hp": 55,
    "attack": 75,
    "defense": 50,
    "special_attack": 40,
    "special_defense": 40,
    "speed": 80,
    "is_restricted": false
  },
  {
    "id": 398,
    "name": "Staraptor",
    "api_name": "staraptor",
    "native_region": "Sinnoh",
    "generation": 4,
    "type_1": "Normal",
    "type_2": "Flying",
    "hp": 85,
    "attack": 120,
    "defense": 70,
    "special_attack": 50,
    "special_defense": 60,
    "speed": 100,
    "is_restricted": false
  },
  {
    "id": 399,
    "name": "Bidoof",
    "api_name": "bidoof",
    "native_region": "Sinnoh",
    "generation": 4,
    "type_1": "Normal",
    "type_2": "",
    "hp": 59,
    "attack": 45,
    "defense": 40,
    "special_attack": 35,
    "special_defense": 40,
    "speed": 31,
    "is_restricted": false
  },
  {
    "id": 400,
    "name": "Bibarel",
    "api_name": "bibarel",
    "native_region": "Sinnoh",
    "generation": 4,
    "type_1": "Normal",
    "type_2": "Water",
    "hp": 79,
    "attack": 85,
    "defense": 60,
    "special_attack": 55,
    "special_defense": 60,
    "speed": 71,
    "is_restricted": false
  },
  {
    "id": 401,
    "name": "Kricketot",
    "api_name": "kricketot",
    "native_region": "Sinnoh",
    "generation": 4,
    "type_1": "Bug",
    "type_2": "",
    "hp": 37,
    "attack": 25,
    "defense": 41,
    "special_attack": 25,
    "special_defense": 41,
    "speed": 25,
    "is_restricted": false
  },
  {
    "id": 402,
    "name": "Kricketune",
    "api_name": "kricketune",
    "native_region": "Sinnoh",
    "generation": 4,
    "type_1": "Bug",
    "type_2": "",
    "hp": 77,
    "attack": 85,
    "defense": 51,
    "special_attack": 55,
    "special_defense": 51,
    "speed": 65,
    "is_restricted": false
  },
  {
    "id": 403,
    "name": "Shinx",
    "api_name": "shinx",
    "native_region": "Sinnoh",
    "generation": 4,
    "type_1": "Electric",
    "type_2": "",
    "hp": 45,
    "attack": 65,
    "defense": 34,
    "special_attack": 40,
    "special_defense": 34,
    "speed": 45,
    "is_restricted": false
  },
  {
    "id": 404,
    "name": "Luxio",
    "api_name": "luxio",
    "native_region": "Sinnoh",
    "generation": 4,
    "type_1": "Electric",
    "type_2": "",
    "hp": 60,
    "attack": 85,
    "defense": 49,
    "special_attack": 60,
    "special_defense": 49,
    "speed": 60,
    "is_restricted": false
  },
  {
    "id": 405,
    "name": "Luxray",
    "api_name": "luxray",
    "native_region": "Sinnoh",
    "generation": 4,
    "type_1": "Electric",
    "type_2": "",
    "hp": 80,
    "attack": 120,
    "defense": 79,
    "special_attack": 95,
    "special_defense": 79,
    "speed": 70,
    "is_restricted": false
  },
  {
    "id": 406,
    "name": "Budew",
    "api_name": "budew",
    "native_region": "Sinnoh",
    "generation": 4,
    "type_1": "Grass",
    "type_2": "Poison",
    "hp": 40,
    "attack": 30,
    "defense": 35,
    "special_attack": 50,
    "special_defense": 70,
    "speed": 55,
    "is_restricted": false
  },
  {
    "id": 407,
    "name": "Roserade",
    "api_name": "roserade",
    "native_region": "Sinnoh",
    "generation": 4,
    "type_1": "Grass",
    "type_2": "Poison",
    "hp": 60,
    "attack": 70,
    "defense": 65,
    "special_attack": 125,
    "special_defense": 105,
    "speed": 90,
    "is_restricted": false
  },
  {
    "id": 408,
    "name": "Cranidos",
    "api_name": "cranidos",
    "native_region": "Sinnoh",
    "generation": 4,
    "type_1": "Rock",
    "type_2": "",
    "hp": 67,
    "attack": 125,
    "defense": 40,
    "special_attack": 30,
    "special_defense": 30,
    "speed": 58,
    "is_restricted": false
  },
  {
    "id": 409,
    "name": "Rampardos",
    "api_name": "rampardos",
    "native_region": "Sinnoh",
    "generation": 4,
    "type_1": "Rock",
    "type_2": "",
    "hp": 97,
    "attack": 165,
    "defense": 60,
    "special_attack": 65,
    "special_defense": 50,
    "speed": 58,
    "is_restricted": false
  },
  {
    "id": 410,
    "name": "Shieldon",
    "api_name": "shieldon",
    "native_region": "Sinnoh",
    "generation": 4,
    "type_1": "Rock",
    "type_2": "Steel",
    "hp": 30,
    "attack": 42,
    "defense": 118,
    "special_attack": 42,
    "special_defense": 88,
    "speed": 30,
    "is_restricted": false
  },
  {
    "id": 411,
    "name": "Bastiodon",
    "api_name": "bastiodon",
    "native_region": "Sinnoh",
    "generation": 4,
    "type_1": "Rock",
    "type_2": "Steel",
    "hp": 60,
    "attack": 52,
    "defense": 168,
    "special_attack": 47,
    "special_defense": 138,
    "speed": 30,
    "is_restricted": false
  },
  {
    "id": 412,
    "name": "Burmy",
    "api_name": "burmy",
    "native_region": "Sinnoh",
    "generation": 4,
    "type_1": "Bug",
    "type_2": "",
    "hp": 40,
    "attack": 29,
    "defense": 45,
    "special_attack": 29,
    "special_defense": 45,
    "speed": 36,
    "is_restricted": false
  },
  {
    "id": 413,
    "name": "Wormadam",
    "api_name": "wormadam-plant",
    "native_region": "Sinnoh",
    "generation": 4,
    "type_1": "Bug",
    "type_2": "Grass",
    "hp": 60,
    "attack": 59,
    "defense": 85,
    "special_attack": 79,
    "special_defense": 105,
    "speed": 36,
    "is_restricted": false
  },
  {
    "id": 414,
    "name": "Mothim",
    "api_name": "mothim",
    "native_region": "Sinnoh",
    "generation": 4,
    "type_1": "Bug",
    "type_2": "Flying",
    "hp": 70,
    "attack": 94,
    "defense": 50,
    "special_attack": 94,
    "special_defense": 50,
    "speed": 66,
    "is_restricted": false
  },
  {
    "id": 415,
    "name": "Combee",
    "api_name": "combee",
    "native_region": "Sinnoh",
    "generation": 4,
    "type_1": "Bug",
    "type_2": "Flying",
    "hp": 30,
    "attack": 30,
    "defense": 42,
    "special_attack": 30,
    "special_defense": 42,
    "speed": 70,
    "is_restricted": false
  },
  {
    "id": 416,
    "name": "Vespiquen",
    "api_name": "vespiquen",
    "native_region": "Sinnoh",
    "generation": 4,
    "type_1": "Bug",
    "type_2": "Flying",
    "hp": 70,
    "attack": 80,
    "defense": 102,
    "special_attack": 80,
    "special_defense": 102,
    "speed": 40,
    "is_restricted": false
  },
  {
    "id": 417,
    "name": "Pachirisu",
    "api_name": "pachirisu",
    "native_region": "Sinnoh",
    "generation": 4,
    "type_1": "Electric",
    "type_2": "",
    "hp": 60,
    "attack": 45,
    "defense": 70,
    "special_attack": 45,
    "special_defense": 90,
    "speed": 95,
    "is_restricted": false
  },
  {
    "id": 418,
    "name": "Buizel",
    "api_name": "buizel",
    "native_region": "Sinnoh",
    "generation": 4,
    "type_1": "Water",
    "type_2": "",
    "hp": 55,
    "attack": 65,
    "defense": 35,
    "special_attack": 60,
    "special_defense": 30,
    "speed": 85,
    "is_restricted": false
  },
  {
    "id": 419,
    "name": "Floatzel",
    "api_name": "floatzel",
    "native_region": "Sinnoh",
    "generation": 4,
    "type_1": "Water",
    "type_2": "",
    "hp": 85,
    "attack": 105,
    "defense": 55,
    "special_attack": 85,
    "special_defense": 50,
    "speed": 115,
    "is_restricted": false
  },
  {
    "id": 420,
    "name": "Cherubi",
    "api_name": "cherubi",
    "native_region": "Sinnoh",
    "generation": 4,
    "type_1": "Grass",
    "type_2": "",
    "hp": 45,
    "attack": 35,
    "defense": 45,
    "special_attack": 62,
    "special_defense": 53,
    "speed": 35,
    "is_restricted": false
  },
  {
    "id": 421,
    "name": "Cherrim",
    "api_name": "cherrim",
    "native_region": "Sinnoh",
    "generation": 4,
    "type_1": "Grass",
    "type_2": "",
    "hp": 70,
    "attack": 60,
    "defense": 70,
    "special_attack": 87,
    "special_defense": 78,
    "speed": 85,
    "is_restricted": false
  },
  {
    "id": 422,
    "name": "Shellos",
    "api_name": "shellos",
    "native_region": "Sinnoh",
    "generation": 4,
    "type_1": "Water",
    "type_2": "",
    "hp": 76,
    "attack": 48,
    "defense": 48,
    "special_attack": 57,
    "special_defense": 62,
    "speed": 34,
    "is_restricted": false
  },
  {
    "id": 423,
    "name": "Gastrodon",
    "api_name": "gastrodon",
    "native_region": "Sinnoh",
    "generation": 4,
    "type_1": "Water",
    "type_2": "Ground",
    "hp": 111,
    "attack": 83,
    "defense": 68,
    "special_attack": 92,
    "special_defense": 82,
    "speed": 39,
    "is_restricted": false
  },
  {
    "id": 424,
    "name": "Ambipom",
    "api_name": "ambipom",
    "native_region": "Sinnoh",
    "generation": 4,
    "type_1": "Normal",
    "type_2": "",
    "hp": 75,
    "attack": 100,
    "defense": 66,
    "special_attack": 60,
    "special_defense": 66,
    "speed": 115,
    "is_restricted": false
  },
  {
    "id": 425,
    "name": "Drifloon",
    "api_name": "drifloon",
    "native_region": "Sinnoh",
    "generation": 4,
    "type_1": "Ghost",
    "type_2": "Flying",
    "hp": 90,
    "attack": 50,
    "defense": 34,
    "special_attack": 60,
    "special_defense": 44,
    "speed": 70,
    "is_restricted": false
  },
  {
    "id": 426,
    "name": "Drifblim",
    "api_name": "drifblim",
    "native_region": "Sinnoh",
    "generation": 4,
    "type_1": "Ghost",
    "type_2": "Flying",
    "hp": 150,
    "attack": 80,
    "defense": 44,
    "special_attack": 90,
    "special_defense": 54,
    "speed": 80,
    "is_restricted": false
  },
  {
    "id": 427,
    "name": "Buneary",
    "api_name": "buneary",
    "native_region": "Sinnoh",
    "generation": 4,
    "type_1": "Normal",
    "type_2": "",
    "hp": 55,
    "attack": 66,
    "defense": 44,
    "special_attack": 44,
    "special_defense": 56,
    "speed": 85,
    "is_restricted": false
  },
  {
    "id": 428,
    "name": "Lopunny",
    "api_name": "lopunny",
    "native_region": "Sinnoh",
    "generation": 4,
    "type_1": "Normal",
    "type_2": "",
    "hp": 65,
    "attack": 76,
    "defense": 84,
    "special_attack": 54,
    "special_defense": 96,
    "speed": 105,
    "is_restricted": false
  },
  {
    "id": 429,
    "name": "Mismagius",
    "api_name": "mismagius",
    "native_region": "Sinnoh",
    "generation": 4,
    "type_1": "Ghost",
    "type_2": "",
    "hp": 60,
    "attack": 60,
    "defense": 60,
    "special_attack": 105,
    "special_defense": 105,
    "speed": 105,
    "is_restricted": false
  },
  {
    "id": 430,
    "name": "Honchkrow",
    "api_name": "honchkrow",
    "native_region": "Sinnoh",
    "generation": 4,
    "type_1": "Dark",
    "type_2": "Flying",
    "hp": 100,
    "attack": 125,
    "defense": 52,
    "special_attack": 105,
    "special_defense": 52,
    "speed": 71,
    "is_restricted": false
  },
  {
    "id": 431,
    "name": "Glameow",
    "api_name": "glameow",
    "native_region": "Sinnoh",
    "generation": 4,
    "type_1": "Normal",
    "type_2": "",
    "hp": 49,
    "attack": 55,
    "defense": 42,
    "special_attack": 42,
    "special_defense": 37,
    "speed": 85,
    "is_restricted": false
  },
  {
    "id": 432,
    "name": "Purugly",
    "api_name": "purugly",
    "native_region": "Sinnoh",
    "generation": 4,
    "type_1": "Normal",
    "type_2": "",
    "hp": 71,
    "attack": 82,
    "defense": 64,
    "special_attack": 64,
    "special_defense": 59,
    "speed": 112,
    "is_restricted": false
  },
  {
    "id": 433,
    "name": "Chingling",
    "api_name": "chingling",
    "native_region": "Sinnoh",
    "generation": 4,
    "type_1": "Psychic",
    "type_2": "",
    "hp": 45,
    "attack": 30,
    "defense": 50,
    "special_attack": 65,
    "special_defense": 50,
    "speed": 45,
    "is_restricted": false
  },
  {
    "id": 434,
    "name": "Stunky",
    "api_name": "stunky",
    "native_region": "Sinnoh",
    "generation": 4,
    "type_1": "Poison",
    "type_2": "Dark",
    "hp": 63,
    "attack": 63,
    "defense": 47,
    "special_attack": 41,
    "special_defense": 41,
    "speed": 74,
    "is_restricted": false
  },
  {
    "id": 435,
    "name": "Skuntank",
    "api_name": "skuntank",
    "native_region": "Sinnoh",
    "generation": 4,
    "type_1": "Poison",
    "type_2": "Dark",
    "hp": 103,
    "attack": 93,
    "defense": 67,
    "special_attack": 71,
    "special_defense": 61,
    "speed": 84,
    "is_restricted": false
  },
  {
    "id": 436,
    "name": "Bronzor",
    "api_name": "bronzor",
    "native_region": "Sinnoh",
    "generation": 4,
    "type_1": "Steel",
    "type_2": "Psychic",
    "hp": 57,
    "attack": 24,
    "defense": 86,
    "special_attack": 24,
    "special_defense": 86,
    "speed": 23,
    "is_restricted": false
  },
  {
    "id": 437,
    "name": "Bronzong",
    "api_name": "bronzong",
    "native_region": "Sinnoh",
    "generation": 4,
    "type_1": "Steel",
    "type_2": "Psychic",
    "hp": 67,
    "attack": 89,
    "defense": 116,
    "special_attack": 79,
    "special_defense": 116,
    "speed": 33,
    "is_restricted": false
  },
  {
    "id": 438,
    "name": "Bonsly",
    "api_name": "bonsly",
    "native_region": "Sinnoh",
    "generation": 4,
    "type_1": "Rock",
    "type_2": "",
    "hp": 50,
    "attack": 80,
    "defense": 95,
    "special_attack": 10,
    "special_defense": 45,
    "speed": 10,
    "is_restricted": false
  },
  {
    "id": 439,
    "name": "Mime Jr.",
    "api_name": "mime-jr",
    "native_region": "Sinnoh",
    "generation": 4,
    "type_1": "Psychic",
    "type_2": "Fairy",
    "hp": 20,
    "attack": 25,
    "defense": 45,
    "special_attack": 70,
    "special_defense": 90,
    "speed": 60,
    "is_restricted": false
  },
  {
    "id": 440,
    "name": "Happiny",
    "api_name": "happiny",
    "native_region": "Sinnoh",
    "generation": 4,
    "type_1": "Normal",
    "type_2": "",
    "hp": 100,
    "attack": 5,
    "defense": 5,
    "special_attack": 15,
    "special_defense": 65,
    "speed": 30,
    "is_restricted": false
  },
  {
    "id": 441,
    "name": "Chatot",
    "api_name": "chatot",
    "native_region": "Sinnoh",
    "generation": 4,
    "type_1": "Normal",
    "type_2": "Flying",
    "hp": 76,
    "attack": 65,
    "defense": 45,
    "special_attack": 92,
    "special_defense": 42,
    "speed": 91,
    "is_restricted": false
  },
  {
    "id": 442,
    "name": "Spiritomb",
    "api_name": "spiritomb",
    "native_region": "Sinnoh",
    "generation": 4,
    "type_1": "Ghost",
    "type_2": "Dark",
    "hp": 50,
    "attack": 92,
    "defense": 108,
    "special_attack": 92,
    "special_defense": 108,
    "speed": 35,
    "is_restricted": false
  },
  {
    "id": 443,
    "name": "Gible",
    "api_name": "gible",
    "native_region": "Sinnoh",
    "generation": 4,
    "type_1": "Dragon",
    "type_2": "Ground",
    "hp": 58,
    "attack": 70,
    "defense": 45,
    "special_attack": 40,
    "special_defense": 45,
    "speed": 42,
    "is_restricted": false
  },
  {
    "id": 444,
    "name": "Gabite",
    "api_name": "gabite",
    "native_region": "Sinnoh",
    "generation": 4,
    "type_1": "Dragon",
    "type_2": "Ground",
    "hp": 68,
    "attack": 90,
    "defense": 65,
    "special_attack": 50,
    "special_defense": 55,
    "speed": 82,
    "is_restricted": false
  },
  {
    "id": 445,
    "name": "Garchomp",
    "api_name": "garchomp",
    "native_region": "Sinnoh",
    "generation": 4,
    "type_1": "Dragon",
    "type_2": "Ground",
    "hp": 108,
    "attack": 130,
    "defense": 95,
    "special_attack": 80,
    "special_defense": 85,
    "speed": 102,
    "is_restricted": false
  },
  {
    "id": 446,
    "name": "Munchlax",
    "api_name": "munchlax",
    "native_region": "Sinnoh",
    "generation": 4,
    "type_1": "Normal",
    "type_2": "",
    "hp": 135,
    "attack": 85,
    "defense": 40,
    "special_attack": 40,
    "special_defense": 85,
    "speed": 5,
    "is_restricted": false
  },
  {
    "id": 447,
    "name": "Riolu",
    "api_name": "riolu",
    "native_region": "Sinnoh",
    "generation": 4,
    "type_1": "Fighting",
    "type_2": "",
    "hp": 40,
    "attack": 70,
    "defense": 40,
    "special_attack": 35,
    "special_defense": 40,
    "speed": 60,
    "is_restricted": false
  },
  {
    "id": 448,
    "name": "Lucario",
    "api_name": "lucario",
    "native_region": "Sinnoh",
    "generation": 4,
    "type_1": "Fighting",
    "type_2": "Steel",
    "hp": 70,
    "attack": 110,
    "defense": 70,
    "special_attack": 115,
    "special_defense": 70,
    "speed": 90,
    "is_restricted": false
  },
  {
    "id": 449,
    "name": "Hippopotas",
    "api_name": "hippopotas",
    "native_region": "Sinnoh",
    "generation": 4,
    "type_1": "Ground",
    "type_2": "",
    "hp": 68,
    "attack": 72,
    "defense": 78,
    "special_attack": 38,
    "special_defense": 42,
    "speed": 32,
    "is_restricted": false
  },
  {
    "id": 450,
    "name": "Hippowdon",
    "api_name": "hippowdon",
    "native_region": "Sinnoh",
    "generation": 4,
    "type_1": "Ground",
    "type_2": "",
    "hp": 108,
    "attack": 112,
    "defense": 118,
    "special_attack": 68,
    "special_defense": 72,
    "speed": 47,
    "is_restricted": false
  },
  {
    "id": 451,
    "name": "Skorupi",
    "api_name": "skorupi",
    "native_region": "Sinnoh",
    "generation": 4,
    "type_1": "Poison",
    "type_2": "Bug",
    "hp": 40,
    "attack": 50,
    "defense": 90,
    "special_attack": 30,
    "special_defense": 55,
    "speed": 65,
    "is_restricted": false
  },
  {
    "id": 452,
    "name": "Drapion",
    "api_name": "drapion",
    "native_region": "Sinnoh",
    "generation": 4,
    "type_1": "Poison",
    "type_2": "Dark",
    "hp": 70,
    "attack": 90,
    "defense": 110,
    "special_attack": 60,
    "special_defense": 75,
    "speed": 95,
    "is_restricted": false
  },
  {
    "id": 453,
    "name": "Croagunk",
    "api_name": "croagunk",
    "native_region": "Sinnoh",
    "generation": 4,
    "type_1": "Poison",
    "type_2": "Fighting",
    "hp": 48,
    "attack": 61,
    "defense": 40,
    "special_attack": 61,
    "special_defense": 40,
    "speed": 50,
    "is_restricted": false
  },
  {
    "id": 454,
    "name": "Toxicroak",
    "api_name": "toxicroak",
    "native_region": "Sinnoh",
    "generation": 4,
    "type_1": "Poison",
    "type_2": "Fighting",
    "hp": 83,
    "attack": 106,
    "defense": 65,
    "special_attack": 86,
    "special_defense": 65,
    "speed": 85,
    "is_restricted": false
  },
  {
    "id": 455,
    "name": "Carnivine",
    "api_name": "carnivine",
    "native_region": "Sinnoh",
    "generation": 4,
    "type_1": "Grass",
    "type_2": "",
    "hp": 74,
    "attack": 100,
    "defense": 72,
    "special_attack": 90,
    "special_defense": 72,
    "speed": 46,
    "is_restricted": false
  },
  {
    "id": 456,
    "name": "Finneon",
    "api_name": "finneon",
    "native_region": "Sinnoh",
    "generation": 4,
    "type_1": "Water",
    "type_2": "",
    "hp": 49,
    "attack": 49,
    "defense": 56,
    "special_attack": 49,
    "special_defense": 61,
    "speed": 66,
    "is_restricted": false
  },
  {
    "id": 457,
    "name": "Lumineon",
    "api_name": "lumineon",
    "native_region": "Sinnoh",
    "generation": 4,
    "type_1": "Water",
    "type_2": "",
    "hp": 69,
    "attack": 69,
    "defense": 76,
    "special_attack": 69,
    "special_defense": 86,
    "speed": 91,
    "is_restricted": false
  },
  {
    "id": 458,
    "name": "Mantyke",
    "api_name": "mantyke",
    "native_region": "Sinnoh",
    "generation": 4,
    "type_1": "Water",
    "type_2": "Flying",
    "hp": 45,
    "attack": 20,
    "defense": 50,
    "special_attack": 60,
    "special_defense": 120,
    "speed": 50,
    "is_restricted": false
  },
  {
    "id": 459,
    "name": "Snover",
    "api_name": "snover",
    "native_region": "Sinnoh",
    "generation": 4,
    "type_1": "Grass",
    "type_2": "Ice",
    "hp": 60,
    "attack": 62,
    "defense": 50,
    "special_attack": 62,
    "special_defense": 60,
    "speed": 40,
    "is_restricted": false
  },
  {
    "id": 460,
    "name": "Abomasnow",
    "api_name": "abomasnow",
    "native_region": "Sinnoh",
    "generation": 4,
    "type_1": "Grass",
    "type_2": "Ice",
    "hp": 90,
    "attack": 92,
    "defense": 75,
    "special_attack": 92,
    "special_defense": 85,
    "speed": 60,
    "is_restricted": false
  },
  {
    "id": 461,
    "name": "Weavile",
    "api_name": "weavile",
    "native_region": "Sinnoh",
    "generation": 4,
    "type_1": "Dark",
    "type_2": "Ice",
    "hp": 70,
    "attack": 120,
    "defense": 65,
    "special_attack": 45,
    "special_defense": 85,
    "speed": 125,
    "is_restricted": false
  },
  {
    "id": 462,
    "name": "Magnezone",
    "api_name": "magnezone",
    "native_region": "Sinnoh",
    "generation": 4,
    "type_1": "Electric",
    "type_2": "Steel",
    "hp": 70,
    "attack": 70,
    "defense": 115,
    "special_attack": 130,
    "special_defense": 90,
    "speed": 60,
    "is_restricted": false
  },
  {
    "id": 463,
    "name": "Lickilicky",
    "api_name": "lickilicky",
    "native_region": "Sinnoh",
    "generation": 4,
    "type_1": "Normal",
    "type_2": "",
    "hp": 110,
    "attack": 85,
    "defense": 95,
    "special_attack": 80,
    "special_defense": 95,
    "speed": 50,
    "is_restricted": false
  },
  {
    "id": 464,
    "name": "Rhyperior",
    "api_name": "rhyperior",
    "native_region": "Sinnoh",
    "generation": 4,
    "type_1": "Ground",
    "type_2": "Rock",
    "hp": 115,
    "attack": 140,
    "defense": 130,
    "special_attack": 55,
    "special_defense": 55,
    "speed": 40,
    "is_restricted": false
  },
  {
    "id": 465,
    "name": "Tangrowth",
    "api_name": "tangrowth",
    "native_region": "Sinnoh",
    "generation": 4,
    "type_1": "Grass",
    "type_2": "",
    "hp": 100,
    "attack": 100,
    "defense": 125,
    "special_attack": 110,
    "special_defense": 50,
    "speed": 50,
    "is_restricted": false
  },
  {
    "id": 466,
    "name": "Electivire",
    "api_name": "electivire",
    "native_region": "Sinnoh",
    "generation": 4,
    "type_1": "Electric",
    "type_2": "",
    "hp": 75,
    "attack": 123,
    "defense": 67,
    "special_attack": 95,
    "special_defense": 85,
    "speed": 95,
    "is_restricted": false
  },
  {
    "id": 467,
    "name": "Magmortar",
    "api_name": "magmortar",
    "native_region": "Sinnoh",
    "generation": 4,
    "type_1": "Fire",
    "type_2": "",
    "hp": 75,
    "attack": 95,
    "defense": 67,
    "special_attack": 125,
    "special_defense": 95,
    "speed": 83,
    "is_restricted": false
  },
  {
    "id": 468,
    "name": "Togekiss",
    "api_name": "togekiss",
    "native_region": "Sinnoh",
    "generation": 4,
    "type_1": "Fairy",
    "type_2": "Flying",
    "hp": 85,
    "attack": 50,
    "defense": 95,
    "special_attack": 120,
    "special_defense": 115,
    "speed": 80,
    "is_restricted": false
  },
  {
    "id": 469,
    "name": "Yanmega",
    "api_name": "yanmega",
    "native_region": "Sinnoh",
    "generation": 4,
    "type_1": "Bug",
    "type_2": "Flying",
    "hp": 86,
    "attack": 76,
    "defense": 86,
    "special_attack": 116,
    "special_defense": 56,
    "speed": 95,
    "is_restricted": false
  },
  {
    "id": 470,
    "name": "Leafeon",
    "api_name": "leafeon",
    "native_region": "Sinnoh",
    "generation": 4,
    "type_1": "Grass",
    "type_2": "",
    "hp": 65,
    "attack": 110,
    "defense": 130,
    "special_attack": 60,
    "special_defense": 65,
    "speed": 95,
    "is_restricted": false
  },
  {
    "id": 471,
    "name": "Glaceon",
    "api_name": "glaceon",
    "native_region": "Sinnoh",
    "generation": 4,
    "type_1": "Ice",
    "type_2": "",
    "hp": 65,
    "attack": 60,
    "defense": 110,
    "special_attack": 130,
    "special_defense": 95,
    "speed": 65,
    "is_restricted": false
  },
  {
    "id": 472,
    "name": "Gliscor",
    "api_name": "gliscor",
    "native_region": "Sinnoh",
    "generation": 4,
    "type_1": "Ground",
    "type_2": "Flying",
    "hp": 75,
    "attack": 95,
    "defense": 125,
    "special_attack": 45,
    "special_defense": 75,
    "speed": 95,
    "is_restricted": false
  },
  {
    "id": 473,
    "name": "Mamoswine",
    "api_name": "mamoswine",
    "native_region": "Sinnoh",
    "generation": 4,
    "type_1": "Ice",
    "type_2": "Ground",
    "hp": 110,
    "attack": 130,
    "defense": 80,
    "special_attack": 70,
    "special_defense": 60,
    "speed": 80,
    "is_restricted": false
  },
  {
    "id": 474,
    "name": "Porygon-Z",
    "api_name": "porygon-z",
    "native_region": "Sinnoh",
    "generation": 4,
    "type_1": "Normal",
    "type_2": "",
    "hp": 85,
    "attack": 80,
    "defense": 70,
    "special_attack": 135,
    "special_defense": 75,
    "speed": 90,
    "is_restricted": false
  },
  {
    "id": 475,
    "name": "Gallade",
    "api_name": "gallade",
    "native_region": "Sinnoh",
    "generation": 4,
    "type_1": "Psychic",
    "type_2": "Fighting",
    "hp": 68,
    "attack": 125,
    "defense": 65,
    "special_attack": 65,
    "special_defense": 115,
    "speed": 80,
    "is_restricted": false
  },
  {
    "id": 476,
    "name": "Probopass",
    "api_name": "probopass",
    "native_region": "Sinnoh",
    "generation": 4,
    "type_1": "Rock",
    "type_2": "Steel",
    "hp": 60,
    "attack": 55,
    "defense": 145,
    "special_attack": 75,
    "special_defense": 150,
    "speed": 40,
    "is_restricted": false
  },
  {
    "id": 477,
    "name": "Dusknoir",
    "api_name": "dusknoir",
    "native_region": "Sinnoh",
    "generation": 4,
    "type_1": "Ghost",
    "type_2": "",
    "hp": 45,
    "attack": 100,
    "defense": 135,
    "special_attack": 65,
    "special_defense": 135,
    "speed": 45,
    "is_restricted": false
  },
  {
    "id": 478,
    "name": "Froslass",
    "api_name": "froslass",
    "native_region": "Sinnoh",
    "generation": 4,
    "type_1": "Ice",
    "type_2": "Ghost",
    "hp": 70,
    "attack": 80,
    "defense": 70,
    "special_attack": 80,
    "special_defense": 70,
    "speed": 110,
    "is_restricted": false
  },
  {
    "id": 810,
    "name": "Grookey",
    "api_name": "grookey",
    "native_region": "Galar",
    "generation": 8,
    "type_1": "Grass",
    "type_2": "",
    "hp": 50,
    "attack": 65,
    "defense": 50,
    "special_attack": 40,
    "special_defense": 40,
    "speed": 65,
    "is_restricted": false
  },
  {
    "id": 811,
    "name": "Thwackey",
    "api_name": "thwackey",
    "native_region": "Galar",
    "generation": 8,
    "type_1": "Grass",
    "type_2": "",
    "hp": 70,
    "attack": 85,
    "defense": 70,
    "special_attack": 55,
    "special_defense": 60,
    "speed": 80,
    "is_restricted": false
  },
  {
    "id": 812,
    "name": "Rillaboom",
    "api_name": "rillaboom",
    "native_region": "Galar",
    "generation": 8,
    "type_1": "Grass",
    "type_2": "",
    "hp": 100,
    "attack": 125,
    "defense": 90,
    "special_attack": 60,
    "special_defense": 70,
    "speed": 85,
    "is_restricted": false
  },
  {
    "id": 813,
    "name": "Scorbunny",
    "api_name": "scorbunny",
    "native_region": "Galar",
    "generation": 8,
    "type_1": "Fire",
    "type_2": "",
    "hp": 50,
    "attack": 71,
    "defense": 40,
    "special_attack": 40,
    "special_defense": 40,
    "speed": 69,
    "is_restricted": false
  },
  {
    "id": 814,
    "name": "Raboot",
    "api_name": "raboot",
    "native_region": "Galar",
    "generation": 8,
    "type_1": "Fire",
    "type_2": "",
    "hp": 65,
    "attack": 86,
    "defense": 60,
    "special_attack": 55,
    "special_defense": 60,
    "speed": 94,
    "is_restricted": false
  },
  {
    "id": 815,
    "name": "Cinderace",
    "api_name": "cinderace",
    "native_region": "Galar",
    "generation": 8,
    "type_1": "Fire",
    "type_2": "",
    "hp": 80,
    "attack": 116,
    "defense": 75,
    "special_attack": 65,
    "special_defense": 75,
    "speed": 119,
    "is_restricted": false
  },
  {
    "id": 816,
    "name": "Sobble",
    "api_name": "sobble",
    "native_region": "Galar",
    "generation": 8,
    "type_1": "Water",
    "type_2": "",
    "hp": 50,
    "attack": 40,
    "defense": 40,
    "special_attack": 70,
    "special_defense": 40,
    "speed": 70,
    "is_restricted": false
  },
  {
    "id": 817,
    "name": "Drizzile",
    "api_name": "drizzile",
    "native_region": "Galar",
    "generation": 8,
    "type_1": "Water",
    "type_2": "",
    "hp": 65,
    "attack": 60,
    "defense": 55,
    "special_attack": 95,
    "special_defense": 55,
    "speed": 90,
    "is_restricted": false
  },
  {
    "id": 818,
    "name": "Inteleon",
    "api_name": "inteleon",
    "native_region": "Galar",
    "generation": 8,
    "type_1": "Water",
    "type_2": "",
    "hp": 70,
    "attack": 85,
    "defense": 65,
    "special_attack": 125,
    "special_defense": 65,
    "speed": 120,
    "is_restricted": false
  },
  {
    "id": 819,
    "name": "Skwovet",
    "api_name": "skwovet",
    "native_region": "Galar",
    "generation": 8,
    "type_1": "Normal",
    "type_2": "",
    "hp": 70,
    "attack": 55,
    "defense": 55,
    "special_attack": 35,
    "special_defense": 35,
    "speed": 25,
    "is_restricted": false
  },
  {
    "id": 820,
    "name": "Greedent",
    "api_name": "greedent",
    "native_region": "Galar",
    "generation": 8,
    "type_1": "Normal",
    "type_2": "",
    "hp": 120,
    "attack": 95,
    "defense": 95,
    "special_attack": 55,
    "special_defense": 75,
    "speed": 20,
    "is_restricted": false
  },
  {
    "id": 821,
    "name": "Rookidee",
    "api_name": "rookidee",
    "native_region": "Galar",
    "generation": 8,
    "type_1": "Flying",
    "type_2": "",
    "hp": 38,
    "attack": 47,
    "defense": 35,
    "special_attack": 33,
    "special_defense": 35,
    "speed": 57,
    "is_restricted": false
  },
  {
    "id": 822,
    "name": "Corvisquire",
    "api_name": "corvisquire",
    "native_region": "Galar",
    "generation": 8,
    "type_1": "Flying",
    "type_2": "",
    "hp": 68,
    "attack": 67,
    "defense": 55,
    "special_attack": 43,
    "special_defense": 55,
    "speed": 77,
    "is_restricted": false
  },
  {
    "id": 823,
    "name": "Corviknight",
    "api_name": "corviknight",
    "native_region": "Galar",
    "generation": 8,
    "type_1": "Flying",
    "type_2": "Steel",
    "hp": 98,
    "attack": 87,
    "defense": 105,
    "special_attack": 53,
    "special_defense": 85,
    "speed": 67,
    "is_restricted": false
  },
  {
    "id": 824,
    "name": "Blipbug",
    "api_name": "blipbug",
    "native_region": "Galar",
    "generation": 8,
    "type_1": "Bug",
    "type_2": "",
    "hp": 25,
    "attack": 20,
    "defense": 20,
    "special_attack": 25,
    "special_defense": 25,
    "speed": 45,
    "is_restricted": false
  },
  {
    "id": 825,
    "name": "Dottler",
    "api_name": "dottler",
    "native_region": "Galar",
    "generation": 8,
    "type_1": "Bug",
    "type_2": "Psychic",
    "hp": 50,
    "attack": 35,
    "defense": 80,
    "special_attack": 50,
    "special_defense": 90,
    "speed": 6,
    "is_restricted": false
  },
  {
    "id": 826,
    "name": "Orbeetle",
    "api_name": "orbeetle",
    "native_region": "Galar",
    "generation": 8,
    "type_1": "Bug",
    "type_2": "Psychic",
    "hp": 60,
    "attack": 45,
    "defense": 110,
    "special_attack": 80,
    "special_defense": 120,
    "speed": 90,
    "is_restricted": false
  },
  {
    "id": 827,
    "name": "Nickit",
    "api_name": "nickit",
    "native_region": "Galar",
    "generation": 8,
    "type_1": "Dark",
    "type_2": "",
    "hp": 40,
    "attack": 28,
    "defense": 28,
    "special_attack": 47,
    "special_defense": 52,
    "speed": 50,
    "is_restricted": false
  },
  {
    "id": 828,
    "name": "Thievul",
    "api_name": "thievul",
    "native_region": "Galar",
    "generation": 8,
    "type_1": "Dark",
    "type_2": "",
    "hp": 70,
    "attack": 58,
    "defense": 58,
    "special_attack": 87,
    "special_defense": 92,
    "speed": 90,
    "is_restricted": false
  },
  {
    "id": 829,
    "name": "Gossifleur",
    "api_name": "gossifleur",
    "native_region": "Galar",
    "generation": 8,
    "type_1": "Grass",
    "type_2": "",
    "hp": 40,
    "attack": 40,
    "defense": 60,
    "special_attack": 40,
    "special_defense": 60,
    "speed": 10,
    "is_restricted": false
  },
  {
    "id": 830,
    "name": "Eldegoss",
    "api_name": "eldegoss",
    "native_region": "Galar",
    "generation": 8,
    "type_1": "Grass",
    "type_2": "",
    "hp": 60,
    "attack": 50,
    "defense": 90,
    "special_attack": 80,
    "special_defense": 120,
    "speed": 60,
    "is_restricted": false
  },
  {
    "id": 831,
    "name": "Wooloo",
    "api_name": "wooloo",
    "native_region": "Galar",
    "generation": 8,
    "type_1": "Normal",
    "type_2": "",
    "hp": 42,
    "attack": 40,
    "defense": 55,
    "special_attack": 40,
    "special_defense": 45,
    "speed": 48,
    "is_restricted": false
  },
  {
    "id": 832,
    "name": "Dubwool",
    "api_name": "dubwool",
    "native_region": "Galar",
    "generation": 8,
    "type_1": "Normal",
    "type_2": "",
    "hp": 72,
    "attack": 80,
    "defense": 100,
    "special_attack": 60,
    "special_defense": 90,
    "speed": 88,
    "is_restricted": false
  },
  {
    "id": 833,
    "name": "Chewtle",
    "api_name": "chewtle",
    "native_region": "Galar",
    "generation": 8,
    "type_1": "Water",
    "type_2": "",
    "hp": 50,
    "attack": 64,
    "defense": 50,
    "special_attack": 38,
    "special_defense": 38,
    "speed": 44,
    "is_restricted": false
  },
  {
    "id": 834,
    "name": "Drednaw",
    "api_name": "drednaw",
    "native_region": "Galar",
    "generation": 8,
    "type_1": "Water",
    "type_2": "Rock",
    "hp": 90,
    "attack": 115,
    "defense": 90,
    "special_attack": 48,
    "special_defense": 68,
    "speed": 74,
    "is_restricted": false
  },
  {
    "id": 835,
    "name": "Yamper",
    "api_name": "yamper",
    "native_region": "Galar",
    "generation": 8,
    "type_1": "Electric",
    "type_2": "",
    "hp": 59,
    "attack": 45,
    "defense": 50,
    "special_attack": 40,
    "special_defense": 50,
    "speed": 26,
    "is_restricted": false
  },
  {
    "id": 836,
    "name": "Boltund",
    "api_name": "boltund",
    "native_region": "Galar",
    "generation": 8,
    "type_1": "Electric",
    "type_2": "",
    "hp": 69,
    "attack": 90,
    "defense": 60,
    "special_attack": 90,
    "special_defense": 60,
    "speed": 121,
    "is_restricted": false
  },
  {
    "id": 837,
    "name": "Rolycoly",
    "api_name": "rolycoly",
    "native_region": "Galar",
    "generation": 8,
    "type_1": "Rock",
    "type_2": "",
    "hp": 30,
    "attack": 40,
    "defense": 50,
    "special_attack": 40,
    "special_defense": 50,
    "speed": 65,
    "is_restricted": false
  },
  {
    "id": 838,
    "name": "Carkol",
    "api_name": "carkol",
    "native_region": "Galar",
    "generation": 8,
    "type_1": "Rock",
    "type_2": "Fire",
    "hp": 80,
    "attack": 60,
    "defense": 90,
    "special_attack": 60,
    "special_defense": 70,
    "speed": 70,
    "is_restricted": false
  },
  {
    "id": 839,
    "name": "Coalossal",
    "api_name": "coalossal",
    "native_region": "Galar",
    "generation": 8,
    "type_1": "Rock",
    "type_2": "Fire",
    "hp": 110,
    "attack": 80,
    "defense": 120,
    "special_attack": 80,
    "special_defense": 90,
    "speed": 30,
    "is_restricted": false
  },
  {
    "id": 840,
    "name": "Applin",
    "api_name": "applin",
    "native_region": "Galar",
    "generation": 8,
    "type_1": "Grass",
    "type_2": "Dragon",
    "hp": 40,
    "attack": 40,
    "defense": 80,
    "special_attack": 40,
    "special_defense": 40,
    "speed": 20,
    "is_restricted": false
  },
  {
    "id": 841,
    "name": "Flapple",
    "api_name": "flapple",
    "native_region": "Galar",
    "generation": 8,
    "type_1": "Grass",
    "type_2": "Dragon",
    "hp": 70,
    "attack": 110,
    "defense": 80,
    "special_attack": 95,
    "special_defense": 60,
    "speed": 70,
    "is_restricted": false
  },
  {
    "id": 842,
    "name": "Appletun",
    "api_name": "appletun",
    "native_region": "Galar",
    "generation": 8,
    "type_1": "Grass",
    "type_2": "Dragon",
    "hp": 110,
    "attack": 85,
    "defense": 80,
    "special_attack": 100,
    "special_defense": 80,
    "speed": 30,
    "is_restricted": false
  },
  {
    "id": 843,
    "name": "Silicobra",
    "api_name": "silicobra",
    "native_region": "Galar",
    "generation": 8,
    "type_1": "Ground",
    "type_2": "",
    "hp": 52,
    "attack": 57,
    "defense": 75,
    "special_attack": 35,
    "special_defense": 50,
    "speed": 40,
    "is_restricted": false
  },
  {
    "id": 844,
    "name": "Sandaconda",
    "api_name": "sandaconda",
    "native_region": "Galar",
    "generation": 8,
    "type_1": "Ground",
    "type_2": "",
    "hp": 72,
    "attack": 107,
    "defense": 125,
    "special_attack": 65,
    "special_defense": 70,
    "speed": 71,
    "is_restricted": false
  },
  {
    "id": 845,
    "name": "Cramorant",
    "api_name": "cramorant",
    "native_region": "Galar",
    "generation": 8,
    "type_1": "Flying",
    "type_2": "Water",
    "hp": 70,
    "attack": 65,
    "defense": 45,
    "special_attack": 75,
    "special_defense": 45,
    "speed": 85,
    "is_restricted": false
  },
  {
    "id": 846,
    "name": "Arrokuda",
    "api_name": "arrokuda",
    "native_region": "Galar",
    "generation": 8,
    "type_1": "Water",
    "type_2": "",
    "hp": 41,
    "attack": 63,
    "defense": 40,
    "special_attack": 40,
    "special_defense": 30,
    "speed": 66,
    "is_restricted": false
  },
  {
    "id": 847,
    "name": "Barraskewda",
    "api_name": "barraskewda",
    "native_region": "Galar",
    "generation": 8,
    "type_1": "Water",
    "type_2": "",
    "hp": 61,
    "attack": 123,
    "defense": 60,
    "special_attack": 60,
    "special_defense": 50,
    "speed": 136,
    "is_restricted": false
  },
  {
    "id": 848,
    "name": "Toxel",
    "api_name": "toxel",
    "native_region": "Galar",
    "generation": 8,
    "type_1": "Electric",
    "type_2": "Poison",
    "hp": 40,
    "attack": 38,
    "defense": 35,
    "special_attack": 54,
    "special_defense": 35,
    "speed": 40,
    "is_restricted": false
  },
  {
    "id": 849,
    "name": "Toxtricity",
    "api_name": "toxtricity-amped",
    "native_region": "Galar",
    "generation": 8,
    "type_1": "Electric",
    "type_2": "Poison",
    "hp": 75,
    "attack": 98,
    "defense": 70,
    "special_attack": 114,
    "special_defense": 70,
    "speed": 75,
    "is_restricted": false
  },
  {
    "id": 850,
    "name": "Sizzlipede",
    "api_name": "sizzlipede",
    "native_region": "Galar",
    "generation": 8,
    "type_1": "Fire",
    "type_2": "Bug",
    "hp": 50,
    "attack": 65,
    "defense": 45,
    "special_attack": 50,
    "special_defense": 50,
    "speed": 45,
    "is_restricted": false
  },
  {
    "id": 851,
    "name": "Centiskorch",
    "api_name": "centiskorch",
    "native_region": "Galar",
    "generation": 8,
    "type_1": "Fire",
    "type_2": "Bug",
    "hp": 100,
    "attack": 115,
    "defense": 65,
    "special_attack": 90,
    "special_defense": 90,
    "speed": 65,
    "is_restricted": false
  },
  {
    "id": 852,
    "name": "Clobbopus",
    "api_name": "clobbopus",
    "native_region": "Galar",
    "generation": 8,
    "type_1": "Fighting",
    "type_2": "",
    "hp": 50,
    "attack": 68,
    "defense": 60,
    "special_attack": 50,
    "special_defense": 50,
    "speed": 32,
    "is_restricted": false
  },
  {
    "id": 853,
    "name": "Grapploct",
    "api_name": "grapploct",
    "native_region": "Galar",
    "generation": 8,
    "type_1": "Fighting",
    "type_2": "",
    "hp": 80,
    "attack": 118,
    "defense": 90,
    "special_attack": 70,
    "special_defense": 80,
    "speed": 42,
    "is_restricted": false
  },
  {
    "id": 854,
    "name": "Sinistea",
    "api_name": "sinistea",
    "native_region": "Galar",
    "generation": 8,
    "type_1": "Ghost",
    "type_2": "",
    "hp": 40,
    "attack": 45,
    "defense": 45,
    "special_attack": 74,
    "special_defense": 54,
    "speed": 50,
    "is_restricted": false
  },
  {
    "id": 855,
    "name": "Polteageist",
    "api_name": "polteageist",
    "native_region": "Galar",
    "generation": 8,
    "type_1": "Ghost",
    "type_2": "",
    "hp": 60,
    "attack": 65,
    "defense": 65,
    "special_attack": 134,
    "special_defense": 114,
    "speed": 70,
    "is_restricted": false
  },
  {
    "id": 856,
    "name": "Hatenna",
    "api_name": "hatenna",
    "native_region": "Galar",
    "generation": 8,
    "type_1": "Psychic",
    "type_2": "",
    "hp": 42,
    "attack": 30,
    "defense": 45,
    "special_attack": 56,
    "special_defense": 53,
    "speed": 39,
    "is_restricted": false
  },
  {
    "id": 857,
    "name": "Hattrem",
    "api_name": "hattrem",
    "native_region": "Galar",
    "generation": 8,
    "type_1": "Psychic",
    "type_2": "",
    "hp": 57,
    "attack": 40,
    "defense": 65,
    "special_attack": 86,
    "special_defense": 73,
    "speed": 49,
    "is_restricted": false
  },
  {
    "id": 858,
    "name": "Hatterene",
    "api_name": "hatterene",
    "native_region": "Galar",
    "generation": 8,
    "type_1": "Psychic",
    "type_2": "Fairy",
    "hp": 57,
    "attack": 90,
    "defense": 95,
    "special_attack": 136,
    "special_defense": 103,
    "speed": 29,
    "is_restricted": false
  },
  {
    "id": 859,
    "name": "Impidimp",
    "api_name": "impidimp",
    "native_region": "Galar",
    "generation": 8,
    "type_1": "Dark",
    "type_2": "Fairy",
    "hp": 45,
    "attack": 45,
    "defense": 30,
    "special_attack": 55,
    "special_defense": 40,
    "speed": 50,
    "is_restricted": false
  },
  {
    "id": 860,
    "name": "Morgrem",
    "api_name": "morgrem",
    "native_region": "Galar",
    "generation": 8,
    "type_1": "Dark",
    "type_2": "Fairy",
    "hp": 65,
    "attack": 60,
    "defense": 45,
    "special_attack": 75,
    "special_defense": 55,
    "speed": 70,
    "is_restricted": false
  },
  {
    "id": 861,
    "name": "Grimmsnarl",
    "api_name": "grimmsnarl",
    "native_region": "Galar",
    "generation": 8,
    "type_1": "Dark",
    "type_2": "Fairy",
    "hp": 95,
    "attack": 120,
    "defense": 65,
    "special_attack": 95,
    "special_defense": 75,
    "speed": 60,
    "is_restricted": false
  },
  {
    "id": 862,
    "name": "Obstagoon",
    "api_name": "obstagoon",
    "native_region": "Galar",
    "generation": 8,
    "type_1": "Dark",
    "type_2": "Normal",
    "hp": 93,
    "attack": 90,
    "defense": 101,
    "special_attack": 60,
    "special_defense": 81,
    "speed": 95,
    "is_restricted": false
  },
  {
    "id": 863,
    "name": "Perrserker",
    "api_name": "perrserker",
    "native_region": "Galar",
    "generation": 8,
    "type_1": "Steel",
    "type_2": "",
    "hp": 70,
    "attack": 110,
    "defense": 100,
    "special_attack": 50,
    "special_defense": 60,
    "speed": 60,
    "is_restricted": false
  },
  {
    "id": 864,
    "name": "Cursola",
    "api_name": "cursola",
    "native_region": "Galar",
    "generation": 8,
    "type_1": "Ghost",
    "type_2": "",
    "hp": 60,
    "attack": 95,
    "defense": 50,
    "special_attack": 145,
    "special_defense": 130,
    "speed": 30,
    "is_restricted": false
  },
  {
    "id": 865,
    "name": "Sirfetch'd",
    "api_name": "sirfetchd",
    "native_region": "Galar",
    "generation": 8,
    "type_1": "Fighting",
    "type_2": "",
    "hp": 62,
    "attack": 135,
    "defense": 95,
    "special_attack": 68,
    "special_defense": 82,
    "speed": 65,
    "is_restricted": false
  },
  {
    "id": 866,
    "name": "Mr. Rime",
    "api_name": "mr-rime",
    "native_region": "Galar",
    "generation": 8,
    "type_1": "Ice",
    "type_2": "Psychic",
    "hp": 80,
    "attack": 85,
    "defense": 75,
    "special_attack": 110,
    "special_defense": 100,
    "speed": 70,
    "is_restricted": false
  },
  {
    "id": 867,
    "name": "Runerigus",
    "api_name": "runerigus",
    "native_region": "Galar",
    "generation": 8,
    "type_1": "Ground",
    "type_2": "Ghost",
    "hp": 58,
    "attack": 95,
    "defense": 145,
    "special_attack": 50,
    "special_defense": 105,
    "speed": 29,
    "is_restricted": false
  },
  {
    "id": 868,
    "name": "Milcery",
    "api_name": "milcery",
    "native_region": "Galar",
    "generation": 8,
    "type_1": "Fairy",
    "type_2": "",
    "hp": 45,
    "attack": 40,
    "defense": 40,
    "special_attack": 50,
    "special_defense": 61,
    "speed": 34,
    "is_restricted": false
  },
  {
    "id": 869,
    "name": "Alcremie",
    "api_name": "alcremie",
    "native_region": "Galar",
    "generation": 8,
    "type_1": "Fairy",
    "type_2": "",
    "hp": 65,
    "attack": 60,
    "defense": 75,
    "special_attack": 110,
    "special_defense": 121,
    "speed": 64,
    "is_restricted": false
  },
  {
    "id": 870,
    "name": "Falinks",
    "api_name": "falinks",
    "native_region": "Galar",
    "generation": 8,
    "type_1": "Fighting",
    "type_2": "",
    "hp": 65,
    "attack": 100,
    "defense": 100,
    "special_attack": 70,
    "special_defense": 60,
    "speed": 75,
    "is_restricted": false
  },
  {
    "id": 871,
    "name": "Pincurchin",
    "api_name": "pincurchin",
    "native_region": "Galar",
    "generation": 8,
    "type_1": "Electric",
    "type_2": "",
    "hp": 48,
    "attack": 101,
    "defense": 95,
    "special_attack": 91,
    "special_defense": 85,
    "speed": 15,
    "is_restricted": false
  },
  {
    "id": 872,
    "name": "Snom",
    "api_name": "snom",
    "native_region": "Galar",
    "generation": 8,
    "type_1": "Ice",
    "type_2": "Bug",
    "hp": 30,
    "attack": 25,
    "defense": 35,
    "special_attack": 45,
    "special_defense": 30,
    "speed": 20,
    "is_restricted": false
  },
  {
    "id": 873,
    "name": "Frosmoth",
    "api_name": "frosmoth",
    "native_region": "Galar",
    "generation": 8,
    "type_1": "Ice",
    "type_2": "Bug",
    "hp": 70,
    "attack": 65,
    "defense": 60,
    "special_attack": 125,
    "special_defense": 90,
    "speed": 65,
    "is_restricted": false
  },
  {
    "id": 874,
    "name": "Stonjourner",
    "api_name": "stonjourner",
    "native_region": "Galar",
    "generation": 8,
    "type_1": "Rock",
    "type_2": "",
    "hp": 100,
    "attack": 125,
    "defense": 135,
    "special_attack": 20,
    "special_defense": 20,
    "speed": 70,
    "is_restricted": false
  },
  {
    "id": 875,
    "name": "Eiscue",
    "api_name": "eiscue-ice",
    "native_region": "Galar",
    "generation": 8,
    "type_1": "Ice",
    "type_2": "",
    "hp": 75,
    "attack": 80,
    "defense": 110,
    "special_attack": 65,
    "special_defense": 90,
    "speed": 50,
    "is_restricted": false
  },
  {
    "id": 876,
    "name": "Indeedee",
    "api_name": "indeedee-male",
    "native_region": "Galar",
    "generation": 8,
    "type_1": "Psychic",
    "type_2": "Normal",
    "hp": 60,
    "attack": 65,
    "defense": 55,
    "special_attack": 105,
    "special_defense": 95,
    "speed": 95,
    "is_restricted": false
  },
  {
    "id": 877,
    "name": "Morpeko",
    "api_name": "morpeko",
    "native_region": "Galar",
    "generation": 8,
    "type_1": "Electric",
    "type_2": "Dark",
    "hp": 58,
    "attack": 95,
    "defense": 58,
    "special_attack": 70,
    "special_defense": 58,
    "speed": 97,
    "is_restricted": false
  },
  {
    "id": 878,
    "name": "Cufant",
    "api_name": "cufant",
    "native_region": "Galar",
    "generation": 8,
    "type_1": "Steel",
    "type_2": "",
    "hp": 72,
    "attack": 80,
    "defense": 49,
    "special_attack": 40,
    "special_defense": 49,
    "speed": 40,
    "is_restricted": false
  },
  {
    "id": 879,
    "name": "Copperajah",
    "api_name": "copperajah",
    "native_region": "Galar",
    "generation": 8,
    "type_1": "Steel",
    "type_2": "",
    "hp": 122,
    "attack": 130,
    "defense": 69,
    "special_attack": 80,
    "special_defense": 69,
    "speed": 30,
    "is_restricted": false
  },
  {
    "id": 880,
    "name": "Dracozolt",
    "api_name": "dracozolt",
    "native_region": "Galar",
    "generation": 8,
    "type_1": "Electric",
    "type_2": "Dragon",
    "hp": 90,
    "attack": 100,
    "defense": 90,
    "special_attack": 80,
    "special_defense": 70,
    "speed": 75,
    "is_restricted": false
  },
  {
    "id": 881,
    "name": "Arctozolt",
    "api_name": "arctozolt",
    "native_region": "Galar",
    "generation": 8,
    "type_1": "Electric",
    "type_2": "Ice",
    "hp": 90,
    "attack": 100,
    "defense": 90,
    "special_attack": 90,
    "special_defense": 80,
    "speed": 55,
    "is_restricted": false
  },
  {
    "id": 882,
    "name": "Dracovish",
    "api_name": "dracovish",
    "native_region": "Galar",
    "generation": 8,
    "type_1": "Water",
    "type_2": "Dragon",
    "hp": 90,
    "attack": 90,
    "defense": 100,
    "special_attack": 70,
    "special_defense": 80,
    "speed": 75,
    "is_restricted": false
  },
  {
    "id": 883,
    "name": "Arctovish",
    "api_name": "arctovish",
    "native_region": "Galar",
    "generation": 8,
    "type_1": "Water",
    "type_2": "Ice",
    "hp": 90,
    "attack": 90,
    "defense": 100,
    "special_attack": 80,
    "special_defense": 90,
    "speed": 55,
    "is_restricted": false
  },
  {
    "id": 884,
    "name": "Duraludon",
    "api_name": "duraludon",
    "native_region": "Galar",
    "generation": 8,
    "type_1": "Steel",
    "type_2": "Dragon",
    "hp": 70,
    "attack": 95,
    "defense": 115,
    "special_attack": 120,
    "special_defense": 50,
    "speed": 85,
    "is_restricted": false
  },
  {
    "id": 885,
    "name": "Dreepy",
    "api_name": "dreepy",
    "native_region": "Galar",
    "generation": 8,
    "type_1": "Dragon",
    "type_2": "Ghost",
    "hp": 28,
    "attack": 60,
    "defense": 30,
    "special_attack": 40,
    "special_defense": 30,
    "speed": 82,
    "is_restricted": false
  },
  {
    "id": 886,
    "name": "Drakloak",
    "api_name": "drakloak",
    "native_region": "Galar",
    "generation": 8,
    "type_1": "Dragon",
    "type_2": "Ghost",
    "hp": 68,
    "attack": 80,
    "defense": 50,
    "special_attack": 60,
    "special_defense": 50,
    "speed": 102,
    "is_restricted": false
  },
  {
    "id": 887,
    "name": "Dragapult",
    "api_name": "dragapult",
    "native_region": "Galar",
    "generation": 8,
    "type_1": "Dragon",
    "type_2": "Ghost",
    "hp": 88,
    "attack": 120,
    "defense": 75,
    "special_attack": 100,
    "special_defense": 75,
    "speed": 142,
    "is_restricted": false
  }
]